[
{"pronto_code": "0x0000, 0x0073, 0x0000, 0x000C, 0x0020, 0x0020, 0x0040, 0x0040, 0x0040, 0x0020, 0x0020, 0x0020, 0x0020, 0x0020, 0x0020, 0x0020, 0x0020, 0x0020, 0x0020, 0x0020, 0x0020, 0x0020, 0x0020, 0x0020, 0x0020, 0x0020, 0x0020, 0x0CC8", "protocol": "RC5", "subdevice": "-1", "deviceName": "Unknown_AV200", "device": "16", "key_name": "KEY_SAT", "company": "Arcam", "code_len": 28, "remoteName": "16_-1", "key_code": "0"},
{"pronto_code": "0x0000, 0x0073, 0x0000, 0x000B, 0x0020, 0x0020, 0x0040, 0x0040, 0x0040, 0x0020, 0x0020, 0x0020, 0x0020, 0x0020, 0x0020, 0x0020, 0x0020, 0x0020, 0x0020, 0x0020, 0x0020, 0x0020, 0x0020, 0x0040, 0x0040, 0x0CC8", "protocol": "RC5", "subdevice": "-1", "deviceName": "Unknown_AV200", "device": "16", "key_name": "KEY_1", "company": "Arcam", "code_len": 26, "remoteName": "16_-1", "key_code": "2"},
{"pronto_code": "0x0000, 0x0073, 0x0000, 0x000B, 0x0020, 0x0020, 0x0040, 0x0040, 0x0040, 0x0020, 0x0020, 0x0020, 0x0020, 0x0020, 0x0020, 0x0020, 0x0020, 0x0020, 0x0020, 0x0020, 0x0020, 0x0040, 0x0040, 0x0020, 0x0020, 0x0CC8", "protocol": "RC5", "subdevice": "-1", "deviceName": "Unknown_AV200", "device": "16", "key_name": "KEY_DVD", "company": "Arcam", "code_len": 26, "remoteName": "16_-1", "key_code": "4"},
{"pronto_code": "0x0000, 0x0073, 0x0000, 0x000B, 0x0020, 0x0020, 0x0040, 0x0040, 0x0040, 0x0020, 0x0020, 0x0020, 0x0020, 0x0020, 0x0020, 0x0020, 0x0020, 0x0020, 0x0020, 0x0020, 0x0020, 0x0040, 0x0040, 0x0040, 0x0020, 0x0CA8", "protocol": "RC5", "subdevice": "-1", "deviceName": "Unknown_AV200", "device": "16", "key_name": "KEY_TAPE", "company": "Arcam", "code_len": 26, "remoteName": "16_-1", "key_code": "5"},
{"pronto_code": "0x0000, 0x0073, 0x0000, 0x000B, 0x0020, 0x0020, 0x0040, 0x0040, 0x0040, 0x0020, 0x0020, 0x0020, 0x0020, 0x0020, 0x0020, 0x0020, 0x0020, 0x0020, 0x0020, 0x0020, 0x0020, 0x0040, 0x0020, 0x0020, 0x0040, 0x0CC8", "protocol": "RC5", "subdevice": "-1", "deviceName": "Unknown_AV200", "device": "16", "key_name": "KEY_VCR", "company": "Arcam", "code_len": 26, "remoteName": "16_-1", "key_code": "6"},
{"pronto_code": "0x0000, 0x0073, 0x0000, 0x000C, 0x0020, 0x0020, 0x0040, 0x0040, 0x0040, 0x0020, 0x0020, 0x0020, 0x0020, 0x0020, 0x0020, 0x0020, 0x0020, 0x0020, 0x0020, 0x0020, 0x0020, 0x0040, 0x0020, 0x0020, 0x0020, 0x0020, 0x0020, 0x0CA8", "protocol": "RC5", "subdevice": "-1", "deviceName": "Unknown_AV200", "device": "16", "key_name": "KEY_CD", "company": "Arcam", "code_len": 28, "remoteName": "16_-1", "key_code": "7"},
{"pronto_code": "0x0000, 0x0073, 0x0000, 0x000B, 0x0020, 0x0020, 0x0040, 0x0040, 0x0040, 0x0020, 0x0020, 0x0020, 0x0020, 0x0020, 0x0020, 0x0020, 0x0020, 0x0020, 0x0020, 0x0040, 0x0040, 0x0020, 0x0020, 0x0020, 0x0020, 0x0CC8", "protocol": "RC5", "subdevice": "-1", "deviceName": "Unknown_AV200", "device": "16", "key_name": "KEY_AUX", "company": "Arcam", "code_len": 26, "remoteName": "16_-1", "key_code": "8"},
{"pronto_code": "0x0000, 0x0073, 0x0000, 0x000B, 0x0020, 0x0020, 0x0040, 0x0040, 0x0040, 0x0020, 0x0020, 0x0020, 0x0020, 0x0020, 0x0020, 0x0020, 0x0020, 0x0020, 0x0020, 0x0040, 0x0020, 0x0020, 0x0040, 0x0020, 0x0020, 0x0CC8", "protocol": "RC5", "subdevice": "-1", "deviceName": "Unknown_AV200", "device": "16", "key_name": "KEY_POWER", "company": "Arcam", "code_len": 26, "remoteName": "16_-1", "key_code": "12"},
{"pronto_code": "0x0000, 0x0073, 0x0000, 0x000B, 0x0020, 0x0020, 0x0040, 0x0040, 0x0040, 0x0020, 0x0020, 0x0020, 0x0020, 0x0020, 0x0020, 0x0020, 0x0020, 0x0020, 0x0020, 0x0040, 0x0020, 0x0020, 0x0040, 0x0040, 0x0020, 0x0CA8", "protocol": "RC5", "subdevice": "-1", "deviceName": "Unknown_AV200", "device": "16", "key_name": "silent", "company": "Arcam", "code_len": 26, "remoteName": "16_-1", "key_code": "13"},
{"pronto_code": "0x0000, 0x0073, 0x0000, 0x000B, 0x0020, 0x0020, 0x0040, 0x0040, 0x0040, 0x0020, 0x0020, 0x0020, 0x0020, 0x0020, 0x0020, 0x0020, 0x0020, 0x0040, 0x0040, 0x0020, 0x0020, 0x0020, 0x0020, 0x0020, 0x0020, 0x0CC8", "protocol": "RC5", "subdevice": "-1", "deviceName": "Unknown_AV200", "device": "16", "key_name": "KEY_VOLUMEUP", "company": "Arcam", "code_len": 26, "remoteName": "16_-1", "key_code": "16"},
{"pronto_code": "0x0000, 0x0073, 0x0000, 0x000B, 0x0020, 0x0020, 0x0040, 0x0040, 0x0040, 0x0020, 0x0020, 0x0020, 0x0020, 0x0020, 0x0020, 0x0020, 0x0020, 0x0040, 0x0040, 0x0020, 0x0020, 0x0020, 0x0020, 0x0040, 0x0020, 0x0CA8", "protocol": "RC5", "subdevice": "-1", "deviceName": "Unknown_AV200", "device": "16", "key_name": "KEY_VOLUMEDOWN", "company": "Arcam", "code_len": 26, "remoteName": "16_-1", "key_code": "17"},
{"pronto_code": "0x0000, 0x0073, 0x0000, 0x000B, 0x0020, 0x0020, 0x0040, 0x0040, 0x0040, 0x0020, 0x0020, 0x0020, 0x0020, 0x0020, 0x0020, 0x0040, 0x0040, 0x0020, 0x0020, 0x0020, 0x0020, 0x0020, 0x0020, 0x0020, 0x0020, 0x0CC8", "protocol": "RC5", "subdevice": "-1", "deviceName": "Unknown_AV200", "device": "16", "key_name": "KEY_MODE", "company": "Arcam", "code_len": 26, "remoteName": "16_-1", "key_code": "32"},
{"pronto_code": "0x0000, 0x0073, 0x0000, 0x000A, 0x0020, 0x0020, 0x0040, 0x0040, 0x0040, 0x0020, 0x0020, 0x0020, 0x0020, 0x0020, 0x0020, 0x0040, 0x0040, 0x0020, 0x0020, 0x0040, 0x0040, 0x0040, 0x0020, 0x0CA8", "protocol": "RC5", "subdevice": "-1", "deviceName": "Unknown_AV200", "device": "16", "key_name": "trim", "company": "Arcam", "code_len": 24, "remoteName": "16_-1", "key_code": "37"},
{"pronto_code": "0x0000, 0x0073, 0x0000, 0x0009, 0x0020, 0x0020, 0x0040, 0x0040, 0x0040, 0x0020, 0x0020, 0x0020, 0x0020, 0x0020, 0x0020, 0x0040, 0x0040, 0x0040, 0x0040, 0x0040, 0x0040, 0x0CC8", "protocol": "RC5", "subdevice": "-1", "deviceName": "Unknown_AV200", "device": "16", "key_name": "KEY_SLEEP", "company": "Arcam", "code_len": 22, "remoteName": "16_-1", "key_code": "42"},
{"pronto_code": "0x0000, 0x0073, 0x0000, 0x000A, 0x0020, 0x0020, 0x0040, 0x0040, 0x0040, 0x0020, 0x0020, 0x0020, 0x0020, 0x0020, 0x0020, 0x0040, 0x0020, 0x0020, 0x0040, 0x0040, 0x0040, 0x0020, 0x0020, 0x0CC8", "protocol": "RC5", "subdevice": "-1", "deviceName": "Unknown_AV200", "device": "16", "key_name": "am", "company": "Arcam", "code_len": 24, "remoteName": "16_-1", "key_code": "52"},
{"pronto_code": "0x0000, 0x0073, 0x0000, 0x000A, 0x0020, 0x0020, 0x0040, 0x0040, 0x0040, 0x0020, 0x0020, 0x0020, 0x0020, 0x0020, 0x0020, 0x0040, 0x0020, 0x0020, 0x0040, 0x0040, 0x0040, 0x0040, 0x0020, 0x0CA8", "protocol": "RC5", "subdevice": "-1", "deviceName": "Unknown_AV200", "device": "16", "key_name": "KEY_RADIO", "company": "Arcam", "code_len": 24, "remoteName": "16_-1", "key_code": "53"},
{"pronto_code": "0x0000, 0x0073, 0x0000, 0x000A, 0x0020, 0x0020, 0x0040, 0x0040, 0x0040, 0x0020, 0x0020, 0x0020, 0x0020, 0x0020, 0x0020, 0x0040, 0x0020, 0x0020, 0x0040, 0x0040, 0x0020, 0x0020, 0x0040, 0x0CC8", "protocol": "RC5", "subdevice": "-1", "deviceName": "Unknown_AV200", "device": "16", "key_name": "t-mode", "company": "Arcam", "code_len": 24, "remoteName": "16_-1", "key_code": "54"},
{"pronto_code": "0x0000, 0x0073, 0x0000, 0x000B, 0x0020, 0x0020, 0x0040, 0x0040, 0x0040, 0x0020, 0x0020, 0x0020, 0x0020, 0x0020, 0x0020, 0x0040, 0x0020, 0x0020, 0x0040, 0x0040, 0x0020, 0x0020, 0x0020, 0x0020, 0x0020, 0x0CA8", "protocol": "RC5", "subdevice": "-1", "deviceName": "Unknown_AV200", "device": "16", "key_name": "KEY_INFO", "company": "Arcam", "code_len": 26, "remoteName": "16_-1", "key_code": "55"},
{"pronto_code": "0x0000, 0x0073, 0x0000, 0x000B, 0x0020, 0x0020, 0x0040, 0x0040, 0x0040, 0x0020, 0x0020, 0x0020, 0x0020, 0x0020, 0x0020, 0x0040, 0x0020, 0x0020, 0x0020, 0x0020, 0x0040, 0x0020, 0x0020, 0x0020, 0x0020, 0x0CC8", "protocol": "RC5", "subdevice": "-1", "deviceName": "Unknown_AV200", "device": "16", "key_name": "KEY_CHANNELUP", "company": "Arcam", "code_len": 26, "remoteName": "16_-1", "key_code": "56"},
{"pronto_code": "0x0000, 0x0073, 0x0000, 0x000B, 0x0020, 0x0020, 0x0040, 0x0040, 0x0040, 0x0020, 0x0020, 0x0020, 0x0020, 0x0020, 0x0020, 0x0040, 0x0020, 0x0020, 0x0020, 0x0020, 0x0040, 0x0020, 0x0020, 0x0040, 0x0020, 0x0CA8", "protocol": "RC5", "subdevice": "-1", "deviceName": "Unknown_AV200", "device": "16", "key_name": "KEY_CHANNELDOWN", "company": "Arcam", "code_len": 26, "remoteName": "16_-1", "key_code": "57"},
{"pronto_code": "0x0000, 0x0073, 0x0000, 0x000B, 0x0020, 0x0020, 0x0040, 0x0040, 0x0040, 0x0020, 0x0020, 0x0020, 0x0020, 0x0020, 0x0020, 0x0040, 0x0020, 0x0020, 0x0020, 0x0020, 0x0020, 0x0020, 0x0020, 0x0020, 0x0040, 0x0CC8", "protocol": "RC5", "subdevice": "-1", "deviceName": "Unknown_AV200", "device": "16", "key_name": "dyn", "company": "Arcam", "code_len": 26, "remoteName": "16_-1", "key_code": "62"},
{"pronto_code": "0x0000, 0x0073, 0x0000, 0x000B, 0x0040, 0x0020, 0x0020, 0x0040, 0x0040, 0x0020, 0x0020, 0x0020, 0x0020, 0x0020, 0x0020, 0x0020, 0x0020, 0x0040, 0x0040, 0x0020, 0x0020, 0x0020, 0x0020, 0x0020, 0x0020, 0x0CC8", "protocol": "RC5", "subdevice": "-1", "deviceName": "Unknown_AV200", "device": "16", "key_name": "KEY_RIGHT", "company": "Arcam", "code_len": 26, "remoteName": "16_-1", "key_code": "80"},
{"pronto_code": "0x0000, 0x0073, 0x0000, 0x000B, 0x0040, 0x0020, 0x0020, 0x0040, 0x0040, 0x0020, 0x0020, 0x0020, 0x0020, 0x0020, 0x0020, 0x0020, 0x0020, 0x0040, 0x0040, 0x0020, 0x0020, 0x0020, 0x0020, 0x0040, 0x0020, 0x0CA8", "protocol": "RC5", "subdevice": "-1", "deviceName": "Unknown_AV200", "device": "16", "key_name": "KEY_LEFT", "company": "Arcam", "code_len": 26, "remoteName": "16_-1", "key_code": "81"},
{"pronto_code": "0x0000, 0x0073, 0x0000, 0x000A, 0x0040, 0x0020, 0x0020, 0x0040, 0x0040, 0x0020, 0x0020, 0x0020, 0x0020, 0x0020, 0x0020, 0x0020, 0x0020, 0x0040, 0x0040, 0x0040, 0x0040, 0x0040, 0x0020, 0x0CA8", "protocol": "RC5", "subdevice": "-1", "deviceName": "Unknown_AV200", "device": "16", "key_name": "KEY_DOWN", "company": "Arcam", "code_len": 24, "remoteName": "16_-1", "key_code": "85"},
{"pronto_code": "0x0000, 0x0073, 0x0000, 0x000A, 0x0040, 0x0020, 0x0020, 0x0040, 0x0040, 0x0020, 0x0020, 0x0020, 0x0020, 0x0020, 0x0020, 0x0020, 0x0020, 0x0040, 0x0040, 0x0040, 0x0020, 0x0020, 0x0040, 0x0CC8", "protocol": "RC5", "subdevice": "-1", "deviceName": "Unknown_AV200", "device": "16", "key_name": "KEY_UP", "company": "Arcam", "code_len": 24, "remoteName": "16_-1", "key_code": "86"},
{"pronto_code": "0x0000, 0x0073, 0x0000, 0x000B, 0x0040, 0x0020, 0x0020, 0x0040, 0x0040, 0x0020, 0x0020, 0x0020, 0x0020, 0x0020, 0x0020, 0x0020, 0x0020, 0x0040, 0x0040, 0x0040, 0x0020, 0x0020, 0x0020, 0x0020, 0x0020, 0x0CA8", "protocol": "RC5", "subdevice": "-1", "deviceName": "Unknown_AV200", "device": "16", "key_name": "KEY_OK", "company": "Arcam", "code_len": 26, "remoteName": "16_-1", "key_code": "87"},
{"pronto_code": "0x0000, 0x0073, 0x0000, 0x000B, 0x0040, 0x0020, 0x0020, 0x0040, 0x0040, 0x0020, 0x0020, 0x0020, 0x0020, 0x0020, 0x0020, 0x0020, 0x0020, 0x0040, 0x0020, 0x0020, 0x0040, 0x0020, 0x0020, 0x0020, 0x0020, 0x0CC8", "protocol": "RC5", "subdevice": "-1", "deviceName": "Unknown_AV200", "device": "16", "key_name": "test", "company": "Arcam", "code_len": 26, "remoteName": "16_-1", "key_code": "88"}
]