[
{"pronto_code": "0x0000, 0x0073, 0x0000, 0x000C, 0x0020, 0x0020, 0x0040, 0x0020, 0x0020, 0x0020, 0x0020, 0x0020, 0x0020, 0x0020, 0x0020, 0x0020, 0x0020, 0x0020, 0x0020, 0x0020, 0x0020, 0x0040, 0x0020, 0x0020, 0x0040, 0x0020, 0x0020, 0x0CC8", "protocol": "RC5", "subdevice": "-1", "deviceName": "Video Projector", "device": "0", "key_name": "POWER OFF/STANDBY2", "company": "Marantz", "code_len": 28, "remoteName": "0_-1", "key_code": "12"},
{"pronto_code": "0x0000, 0x0073, 0x0000, 0x000C, 0x0020, 0x0020, 0x0040, 0x0020, 0x0020, 0x0020, 0x0020, 0x0020, 0x0020, 0x0020, 0x0020, 0x0020, 0x0020, 0x0020, 0x0020, 0x0020, 0x0020, 0x0040, 0x0020, 0x0020, 0x0040, 0x0020, 0x0020, 0x0CC8", "protocol": "RC5", "subdevice": "-1", "deviceName": "Video Projector", "device": "0", "key_name": "STANDBY - B", "company": "Marantz", "code_len": 28, "remoteName": "0_-1", "key_code": "12"},
{"pronto_code": "0x0000, 0x0073, 0x0000, 0x000C, 0x0020, 0x0020, 0x0040, 0x0020, 0x0020, 0x0020, 0x0020, 0x0020, 0x0020, 0x0020, 0x0020, 0x0020, 0x0020, 0x0020, 0x0020, 0x0020, 0x0020, 0x0040, 0x0020, 0x0020, 0x0040, 0x0040, 0x0020, 0x0CA8", "protocol": "RC5", "subdevice": "-1", "deviceName": "Video Projector", "device": "0", "key_name": "V-MUTE", "company": "Marantz", "code_len": 28, "remoteName": "0_-1", "key_code": "13"},
{"pronto_code": "0x0000, 0x0073, 0x0000, 0x000C, 0x0020, 0x0020, 0x0040, 0x0020, 0x0020, 0x0020, 0x0020, 0x0020, 0x0020, 0x0020, 0x0020, 0x0020, 0x0020, 0x0020, 0x0020, 0x0020, 0x0020, 0x0040, 0x0020, 0x0020, 0x0040, 0x0040, 0x0020, 0x0CA8", "protocol": "RC5", "subdevice": "-1", "deviceName": "Video Projector", "device": "0", "key_name": "VIDEO MUTE", "company": "Marantz", "code_len": 28, "remoteName": "0_-1", "key_code": "13"},
{"pronto_code": "0x0000, 0x0073, 0x0000, 0x000D, 0x0020, 0x0020, 0x0040, 0x0020, 0x0020, 0x0020, 0x0020, 0x0020, 0x0020, 0x0020, 0x0020, 0x0020, 0x0020, 0x0020, 0x0020, 0x0020, 0x0020, 0x0040, 0x0020, 0x0020, 0x0020, 0x0020, 0x0020, 0x0020, 0x0020, 0x0CA8", "protocol": "RC5", "subdevice": "-1", "deviceName": "Video Projector", "device": "0", "key_name": "INFORMATION", "company": "Marantz", "code_len": 30, "remoteName": "0_-1", "key_code": "15"},
{"pronto_code": "0x0000, 0x0073, 0x0000, 0x000D, 0x0020, 0x0020, 0x0040, 0x0020, 0x0020, 0x0020, 0x0020, 0x0020, 0x0020, 0x0020, 0x0020, 0x0020, 0x0020, 0x0020, 0x0020, 0x0020, 0x0020, 0x0040, 0x0020, 0x0020, 0x0020, 0x0020, 0x0020, 0x0020, 0x0020, 0x0CA8", "protocol": "RC5", "subdevice": "-1", "deviceName": "Video Projector", "device": "0", "key_name": "BACK LIGHT", "company": "Marantz", "code_len": 30, "remoteName": "0_-1", "key_code": "15"},
{"pronto_code": "0x0000, 0x0073, 0x0000, 0x000D, 0x0020, 0x0020, 0x0040, 0x0020, 0x0020, 0x0020, 0x0020, 0x0020, 0x0020, 0x0020, 0x0020, 0x0020, 0x0020, 0x0020, 0x0020, 0x0020, 0x0020, 0x0040, 0x0020, 0x0020, 0x0020, 0x0020, 0x0020, 0x0020, 0x0020, 0x0CA8", "protocol": "RC5", "subdevice": "-1", "deviceName": "Video Projector", "device": "0", "key_name": "INFO", "company": "Marantz", "code_len": 30, "remoteName": "0_-1", "key_code": "15"},
{"pronto_code": "0x0000, 0x0073, 0x0000, 0x000C, 0x0020, 0x0020, 0x0040, 0x0020, 0x0020, 0x0020, 0x0020, 0x0020, 0x0020, 0x0020, 0x0020, 0x0020, 0x0020, 0x0020, 0x0020, 0x0040, 0x0020, 0x0020, 0x0020, 0x0020, 0x0040, 0x0020, 0x0020, 0x0CC8", "protocol": "RC5", "subdevice": "-1", "deviceName": "Video Projector", "device": "0", "key_name": "CURSOR UP", "company": "Marantz", "code_len": 28, "remoteName": "0_-1", "key_code": "28"},
{"pronto_code": "0x0000, 0x0073, 0x0000, 0x000C, 0x0020, 0x0020, 0x0040, 0x0020, 0x0020, 0x0020, 0x0020, 0x0020, 0x0020, 0x0020, 0x0020, 0x0020, 0x0020, 0x0020, 0x0020, 0x0040, 0x0020, 0x0020, 0x0020, 0x0020, 0x0040, 0x0020, 0x0020, 0x0CC8", "protocol": "RC5", "subdevice": "-1", "deviceName": "Video Projector", "device": "0", "key_name": "UP", "company": "Marantz", "code_len": 28, "remoteName": "0_-1", "key_code": "28"},
{"pronto_code": "0x0000, 0x0073, 0x0000, 0x000C, 0x0020, 0x0020, 0x0040, 0x0020, 0x0020, 0x0020, 0x0020, 0x0020, 0x0020, 0x0020, 0x0020, 0x0020, 0x0020, 0x0020, 0x0020, 0x0040, 0x0020, 0x0020, 0x0020, 0x0020, 0x0040, 0x0040, 0x0020, 0x0CA8", "protocol": "RC5", "subdevice": "-1", "deviceName": "Video Projector", "device": "0", "key_name": "CURSOR DOWN", "company": "Marantz", "code_len": 28, "remoteName": "0_-1", "key_code": "29"},
{"pronto_code": "0x0000, 0x0073, 0x0000, 0x000C, 0x0020, 0x0020, 0x0040, 0x0020, 0x0020, 0x0020, 0x0020, 0x0020, 0x0020, 0x0020, 0x0020, 0x0020, 0x0020, 0x0020, 0x0020, 0x0040, 0x0020, 0x0020, 0x0020, 0x0020, 0x0040, 0x0040, 0x0020, 0x0CA8", "protocol": "RC5", "subdevice": "-1", "deviceName": "Video Projector", "device": "0", "key_name": "DOWN", "company": "Marantz", "code_len": 28, "remoteName": "0_-1", "key_code": "29"},
{"pronto_code": "0x0000, 0x0073, 0x0000, 0x000D, 0x0020, 0x0020, 0x0040, 0x0020, 0x0020, 0x0020, 0x0020, 0x0020, 0x0020, 0x0020, 0x0020, 0x0020, 0x0020, 0x0020, 0x0020, 0x0040, 0x0020, 0x0020, 0x0020, 0x0020, 0x0020, 0x0020, 0x0020, 0x0020, 0x0020, 0x0CA8", "protocol": "RC5", "subdevice": "-1", "deviceName": "Video Projector", "device": "0", "key_name": "TINT -", "company": "Marantz", "code_len": 30, "remoteName": "0_-1", "key_code": "31"},
{"pronto_code": "0x0000, 0x0073, 0x0000, 0x000C, 0x0020, 0x0020, 0x0040, 0x0020, 0x0020, 0x0020, 0x0020, 0x0020, 0x0020, 0x0020, 0x0020, 0x0020, 0x0020, 0x0040, 0x0040, 0x0020, 0x0020, 0x0040, 0x0020, 0x0020, 0x0020, 0x0020, 0x0020, 0x0CA8", "protocol": "RC5", "subdevice": "-1", "deviceName": "Video Projector", "device": "0", "key_name": "TINT +", "company": "Marantz", "code_len": 28, "remoteName": "0_-1", "key_code": "39"},
{"pronto_code": "0x0000, 0x0073, 0x0000, 0x000B, 0x0020, 0x0020, 0x0040, 0x0020, 0x0020, 0x0020, 0x0020, 0x0020, 0x0020, 0x0020, 0x0020, 0x0020, 0x0020, 0x0040, 0x0040, 0x0040, 0x0040, 0x0040, 0x0020, 0x0020, 0x0020, 0x0CA8", "protocol": "RC5", "subdevice": "-1", "deviceName": "Video Projector", "device": "0", "key_name": "CURSOR RIGHT", "company": "Marantz", "code_len": 26, "remoteName": "0_-1", "key_code": "43"},
{"pronto_code": "0x0000, 0x0073, 0x0000, 0x000B, 0x0020, 0x0020, 0x0040, 0x0020, 0x0020, 0x0020, 0x0020, 0x0020, 0x0020, 0x0020, 0x0020, 0x0020, 0x0020, 0x0040, 0x0040, 0x0040, 0x0040, 0x0040, 0x0020, 0x0020, 0x0020, 0x0CA8", "protocol": "RC5", "subdevice": "-1", "deviceName": "Video Projector", "device": "0", "key_name": "RIGHT", "company": "Marantz", "code_len": 26, "remoteName": "0_-1", "key_code": "43"},
{"pronto_code": "0x0000, 0x0073, 0x0000, 0x000B, 0x0020, 0x0020, 0x0040, 0x0020, 0x0020, 0x0020, 0x0020, 0x0020, 0x0020, 0x0020, 0x0020, 0x0020, 0x0020, 0x0040, 0x0040, 0x0040, 0x0020, 0x0020, 0x0040, 0x0020, 0x0020, 0x0CC8", "protocol": "RC5", "subdevice": "-1", "deviceName": "Video Projector", "device": "0", "key_name": "CURSOR LEFT", "company": "Marantz", "code_len": 26, "remoteName": "0_-1", "key_code": "44"},
{"pronto_code": "0x0000, 0x0073, 0x0000, 0x000B, 0x0020, 0x0020, 0x0040, 0x0020, 0x0020, 0x0020, 0x0020, 0x0020, 0x0020, 0x0020, 0x0020, 0x0020, 0x0020, 0x0040, 0x0040, 0x0040, 0x0020, 0x0020, 0x0040, 0x0020, 0x0020, 0x0CC8", "protocol": "RC5", "subdevice": "-1", "deviceName": "Video Projector", "device": "0", "key_name": "LEFT", "company": "Marantz", "code_len": 26, "remoteName": "0_-1", "key_code": "44"},
{"pronto_code": "0x0000, 0x0073, 0x0000, 0x000B, 0x0020, 0x0020, 0x0040, 0x0020, 0x0020, 0x0020, 0x0020, 0x0020, 0x0020, 0x0020, 0x0020, 0x0020, 0x0020, 0x0040, 0x0040, 0x0040, 0x0020, 0x0020, 0x0040, 0x0040, 0x0020, 0x0CA8", "protocol": "RC5", "subdevice": "-1", "deviceName": "Video Projector", "device": "0", "key_name": "EXIT", "company": "Marantz", "code_len": 26, "remoteName": "0_-1", "key_code": "45"},
{"pronto_code": "0x0000, 0x0073, 0x0000, 0x000B, 0x0020, 0x0020, 0x0040, 0x0020, 0x0020, 0x0020, 0x0020, 0x0020, 0x0020, 0x0020, 0x0020, 0x0020, 0x0020, 0x0040, 0x0040, 0x0040, 0x0020, 0x0020, 0x0020, 0x0020, 0x0040, 0x0CC8", "protocol": "RC5", "subdevice": "-1", "deviceName": "Video Projector", "device": "0", "key_name": "MENU", "company": "Marantz", "code_len": 26, "remoteName": "0_-1", "key_code": "46"},
{"pronto_code": "0x0000, 0x0073, 0x0000, 0x000C, 0x0020, 0x0020, 0x0040, 0x0020, 0x0020, 0x0020, 0x0020, 0x0020, 0x0020, 0x0020, 0x0020, 0x0020, 0x0020, 0x0040, 0x0020, 0x0020, 0x0020, 0x0020, 0x0040, 0x0020, 0x0020, 0x0020, 0x0020, 0x0CC8", "protocol": "RC5", "subdevice": "-1", "deviceName": "Video Projector", "device": "0", "key_name": "INPUT", "company": "Marantz", "code_len": 28, "remoteName": "0_-1", "key_code": "56"},
{"pronto_code": "0x0000, 0x0073, 0x0000, 0x000D, 0x0020, 0x0020, 0x0040, 0x0020, 0x0020, 0x0020, 0x0020, 0x0020, 0x0020, 0x0020, 0x0020, 0x0020, 0x0020, 0x0040, 0x0020, 0x0020, 0x0020, 0x0020, 0x0020, 0x0020, 0x0020, 0x0020, 0x0020, 0x0020, 0x0020, 0x0CA8", "protocol": "RC5", "subdevice": "-1", "deviceName": "Video Projector", "device": "0", "key_name": "POWER ON 2", "company": "Marantz", "code_len": 30, "remoteName": "0_-1", "key_code": "63"},
{"pronto_code": "0x0000, 0x0073, 0x0000, 0x000D, 0x0020, 0x0020, 0x0040, 0x0020, 0x0020, 0x0020, 0x0020, 0x0020, 0x0020, 0x0020, 0x0020, 0x0020, 0x0020, 0x0040, 0x0020, 0x0020, 0x0020, 0x0020, 0x0020, 0x0020, 0x0020, 0x0020, 0x0020, 0x0020, 0x0020, 0x0CA8", "protocol": "RC5", "subdevice": "-1", "deviceName": "Video Projector", "device": "0", "key_name": "POWER ON - B", "company": "Marantz", "code_len": 30, "remoteName": "0_-1", "key_code": "63"},
{"pronto_code": "0x0000, 0x0073, 0x0000, 0x000B, 0x0040, 0x0020, 0x0020, 0x0020, 0x0020, 0x0020, 0x0020, 0x0020, 0x0020, 0x0020, 0x0020, 0x0020, 0x0020, 0x0020, 0x0020, 0x0040, 0x0040, 0x0020, 0x0020, 0x0040, 0x0040, 0x0CC8", "protocol": "RC5", "subdevice": "-1", "deviceName": "Video Projector", "device": "0", "key_name": "MENU ON", "company": "Marantz", "code_len": 26, "remoteName": "0_-1", "key_code": "82"},
{"pronto_code": "0x0000, 0x0073, 0x0000, 0x000C, 0x0040, 0x0020, 0x0020, 0x0020, 0x0020, 0x0020, 0x0020, 0x0020, 0x0020, 0x0020, 0x0020, 0x0020, 0x0020, 0x0020, 0x0020, 0x0040, 0x0040, 0x0020, 0x0020, 0x0040, 0x0020, 0x0020, 0x0020, 0x0CA8", "protocol": "RC5", "subdevice": "-1", "deviceName": "Video Projector", "device": "0", "key_name": "MENU OFF", "company": "Marantz", "code_len": 28, "remoteName": "0_-1", "key_code": "83"},
{"pronto_code": "0x0000, 0x0073, 0x0000, 0x000C, 0x0040, 0x0020, 0x0020, 0x0020, 0x0020, 0x0020, 0x0020, 0x0020, 0x0020, 0x0020, 0x0020, 0x0020, 0x0020, 0x0020, 0x0020, 0x0040, 0x0040, 0x0040, 0x0020, 0x0020, 0x0020, 0x0020, 0x0020, 0x0CA8", "protocol": "RC5", "subdevice": "-1", "deviceName": "Video Projector", "device": "0", "key_name": "ENTER", "company": "Marantz", "code_len": 28, "remoteName": "0_-1", "key_code": "87"},
{"pronto_code": "0x0000, 0x0073, 0x0000, 0x000C, 0x0040, 0x0020, 0x0020, 0x0020, 0x0020, 0x0020, 0x0020, 0x0020, 0x0020, 0x0020, 0x0020, 0x0020, 0x0020, 0x0020, 0x0020, 0x0040, 0x0020, 0x0020, 0x0040, 0x0020, 0x0020, 0x0020, 0x0020, 0x0CC8", "protocol": "RC5", "subdevice": "-1", "deviceName": "Video Projector", "device": "0", "key_name": "PIP ON/OFF", "company": "Marantz", "code_len": 28, "remoteName": "0_-1", "key_code": "88"},
{"pronto_code": "0x0000, 0x0073, 0x0000, 0x000C, 0x0040, 0x0020, 0x0020, 0x0020, 0x0020, 0x0020, 0x0020, 0x0020, 0x0020, 0x0020, 0x0020, 0x0020, 0x0020, 0x0020, 0x0020, 0x0040, 0x0020, 0x0020, 0x0020, 0x0020, 0x0040, 0x0040, 0x0020, 0x0CA8", "protocol": "RC5", "subdevice": "-1", "deviceName": "Video Projector", "device": "0", "key_name": "PIC MODE -FREEZE", "company": "Marantz", "code_len": 28, "remoteName": "0_-1", "key_code": "93"},
{"pronto_code": "0x0000, 0x0073, 0x0000, 0x000C, 0x0040, 0x0020, 0x0020, 0x0020, 0x0020, 0x0020, 0x0020, 0x0020, 0x0020, 0x0020, 0x0020, 0x0020, 0x0020, 0x0020, 0x0020, 0x0040, 0x0020, 0x0020, 0x0020, 0x0020, 0x0040, 0x0040, 0x0020, 0x0CA8", "protocol": "RC5", "subdevice": "-1", "deviceName": "Video Projector", "device": "0", "key_name": "FREEZE", "company": "Marantz", "code_len": 28, "remoteName": "0_-1", "key_code": "93"},
{"pronto_code": "0x0000, 0x0073, 0x0000, 0x000C, 0x0040, 0x0020, 0x0020, 0x0020, 0x0020, 0x0020, 0x0020, 0x0020, 0x0020, 0x0020, 0x0020, 0x0020, 0x0020, 0x0040, 0x0040, 0x0020, 0x0020, 0x0020, 0x0020, 0x0020, 0x0020, 0x0040, 0x0020, 0x0CA8", "protocol": "RC5", "subdevice": "-1", "deviceName": "Video Projector", "device": "0", "key_name": "SMOOTH", "company": "Marantz", "code_len": 28, "remoteName": "0_-1", "key_code": "97"},
{"pronto_code": "0x0000, 0x0073, 0x0000, 0x000B, 0x0040, 0x0020, 0x0020, 0x0020, 0x0020, 0x0020, 0x0020, 0x0020, 0x0020, 0x0020, 0x0020, 0x0020, 0x0020, 0x0040, 0x0040, 0x0040, 0x0040, 0x0020, 0x0020, 0x0040, 0x0020, 0x0CA8", "protocol": "RC5", "subdevice": "-1", "deviceName": "Video Projector", "device": "0", "key_name": "PICTURE SHIFT", "company": "Marantz", "code_len": 26, "remoteName": "0_-1", "key_code": "105"},
{"pronto_code": "0x0000, 0x0073, 0x0000, 0x000B, 0x0040, 0x0020, 0x0020, 0x0020, 0x0020, 0x0020, 0x0020, 0x0020, 0x0020, 0x0020, 0x0020, 0x0020, 0x0020, 0x0040, 0x0020, 0x0020, 0x0040, 0x0040, 0x0040, 0x0020, 0x0020, 0x0CC8", "protocol": "RC5", "subdevice": "-1", "deviceName": "Video Projector", "device": "0", "key_name": "ASPECT -ZOOM", "company": "Marantz", "code_len": 26, "remoteName": "0_-1", "key_code": "116"},
{"pronto_code": "0x0000, 0x0073, 0x0000, 0x000B, 0x0040, 0x0020, 0x0020, 0x0020, 0x0020, 0x0020, 0x0020, 0x0020, 0x0020, 0x0020, 0x0020, 0x0020, 0x0020, 0x0040, 0x0020, 0x0020, 0x0040, 0x0040, 0x0040, 0x0020, 0x0020, 0x0CC8", "protocol": "RC5", "subdevice": "-1", "deviceName": "Video Projector", "device": "0", "key_name": "ZOOM/ZOOM 1", "company": "Marantz", "code_len": 26, "remoteName": "0_-1", "key_code": "116"},
{"pronto_code": "0x0000, 0x0073, 0x0000, 0x000B, 0x0040, 0x0020, 0x0020, 0x0020, 0x0020, 0x0020, 0x0020, 0x0020, 0x0020, 0x0020, 0x0020, 0x0020, 0x0020, 0x0040, 0x0020, 0x0020, 0x0040, 0x0040, 0x0040, 0x0020, 0x0020, 0x0CC8", "protocol": "RC5", "subdevice": "-1", "deviceName": "Video Projector", "device": "0", "key_name": "ZOOM", "company": "Marantz", "code_len": 26, "remoteName": "0_-1", "key_code": "116"},
{"pronto_code": "0x0000, 0x0073, 0x0000, 0x000B, 0x0040, 0x0020, 0x0020, 0x0020, 0x0020, 0x0020, 0x0020, 0x0020, 0x0020, 0x0020, 0x0020, 0x0020, 0x0020, 0x0040, 0x0020, 0x0020, 0x0040, 0x0040, 0x0040, 0x0020, 0x0020, 0x0CC8", "protocol": "RC5", "subdevice": "-1", "deviceName": "Video Projector", "device": "0", "key_name": "ZOOM (ASPECT)", "company": "Marantz", "code_len": 26, "remoteName": "0_-1", "key_code": "116"},
{"pronto_code": "0x0000, 0x0073, 0x0000, 0x000B, 0x0040, 0x0020, 0x0020, 0x0020, 0x0020, 0x0020, 0x0020, 0x0020, 0x0020, 0x0020, 0x0020, 0x0020, 0x0020, 0x0040, 0x0020, 0x0020, 0x0040, 0x0040, 0x0020, 0x0020, 0x0040, 0x0CC8", "protocol": "RC5", "subdevice": "-1", "deviceName": "Video Projector", "device": "0", "key_name": "CINEMA", "company": "Marantz", "code_len": 26, "remoteName": "0_-1", "key_code": "118"},
{"pronto_code": "0x0000, 0x0073, 0x0000, 0x000B, 0x0040, 0x0020, 0x0020, 0x0020, 0x0020, 0x0020, 0x0020, 0x0020, 0x0020, 0x0020, 0x0020, 0x0020, 0x0020, 0x0040, 0x0020, 0x0020, 0x0040, 0x0040, 0x0020, 0x0020, 0x0040, 0x0CC8", "protocol": "RC5", "subdevice": "-1", "deviceName": "Video Projector", "device": "0", "key_name": "CENEMA", "company": "Marantz", "code_len": 26, "remoteName": "0_-1", "key_code": "118"},
{"pronto_code": "0x0000, 0x0073, 0x0000, 0x000C, 0x0040, 0x0020, 0x0020, 0x0020, 0x0020, 0x0020, 0x0020, 0x0020, 0x0020, 0x0020, 0x0020, 0x0020, 0x0020, 0x0040, 0x0020, 0x0020, 0x0040, 0x0040, 0x0020, 0x0020, 0x0020, 0x0020, 0x0020, 0x0CA8", "protocol": "RC5", "subdevice": "-1", "deviceName": "Video Projector", "device": "0", "key_name": "BACK LIGHT", "company": "Marantz", "code_len": 28, "remoteName": "0_-1", "key_code": "119"},
{"pronto_code": "0x0000, 0x0073, 0x0000, 0x000C, 0x0040, 0x0020, 0x0020, 0x0020, 0x0020, 0x0020, 0x0020, 0x0020, 0x0020, 0x0020, 0x0020, 0x0020, 0x0020, 0x0040, 0x0020, 0x0020, 0x0040, 0x0040, 0x0020, 0x0020, 0x0020, 0x0020, 0x0020, 0x0CA8", "protocol": "RC5", "subdevice": "-1", "deviceName": "Video Projector", "device": "0", "key_name": "INFORMATION (OSD)", "company": "Marantz", "code_len": 28, "remoteName": "0_-1", "key_code": "119"},
{"pronto_code": "0x0000, 0x0073, 0x0000, 0x000C, 0x0040, 0x0020, 0x0020, 0x0020, 0x0020, 0x0020, 0x0020, 0x0020, 0x0020, 0x0020, 0x0020, 0x0020, 0x0020, 0x0040, 0x0020, 0x0020, 0x0020, 0x0020, 0x0020, 0x0020, 0x0040, 0x0040, 0x0020, 0x0CA8", "protocol": "RC5", "subdevice": "-1", "deviceName": "Video Projector", "device": "0", "key_name": "ASPECT", "company": "Marantz", "code_len": 28, "remoteName": "0_-1", "key_code": "125"},
{"pronto_code": "0x0000, 0x0073, 0x0000, 0x000C, 0x0040, 0x0020, 0x0020, 0x0020, 0x0020, 0x0020, 0x0020, 0x0020, 0x0020, 0x0020, 0x0020, 0x0020, 0x0020, 0x0040, 0x0020, 0x0020, 0x0020, 0x0020, 0x0020, 0x0020, 0x0020, 0x0020, 0x0040, 0x0CC8", "protocol": "RC5", "subdevice": "-1", "deviceName": "Video Projector", "device": "0", "key_name": "ASPECT -FULL", "company": "Marantz", "code_len": 28, "remoteName": "0_-1", "key_code": "126"},
{"pronto_code": "0x0000, 0x0073, 0x0000, 0x000C, 0x0040, 0x0020, 0x0020, 0x0020, 0x0020, 0x0020, 0x0020, 0x0020, 0x0020, 0x0020, 0x0020, 0x0020, 0x0020, 0x0040, 0x0020, 0x0020, 0x0020, 0x0020, 0x0020, 0x0020, 0x0020, 0x0020, 0x0040, 0x0CC8", "protocol": "RC5", "subdevice": "-1", "deviceName": "Video Projector", "device": "0", "key_name": "ASPECT -SQUEEZE", "company": "Marantz", "code_len": 28, "remoteName": "0_-1", "key_code": "126"},
{"pronto_code": "0x0000, 0x0073, 0x0000, 0x000C, 0x0040, 0x0020, 0x0020, 0x0020, 0x0020, 0x0020, 0x0020, 0x0020, 0x0020, 0x0020, 0x0020, 0x0020, 0x0020, 0x0040, 0x0020, 0x0020, 0x0020, 0x0020, 0x0020, 0x0020, 0x0020, 0x0020, 0x0040, 0x0CC8", "protocol": "RC5", "subdevice": "-1", "deviceName": "Video Projector", "device": "0", "key_name": "FULL SQUEEZE", "company": "Marantz", "code_len": 28, "remoteName": "0_-1", "key_code": "126"},
{"pronto_code": "0x0000, 0x0073, 0x0000, 0x000C, 0x0040, 0x0020, 0x0020, 0x0020, 0x0020, 0x0020, 0x0020, 0x0020, 0x0020, 0x0020, 0x0020, 0x0020, 0x0020, 0x0040, 0x0020, 0x0020, 0x0020, 0x0020, 0x0020, 0x0020, 0x0020, 0x0020, 0x0040, 0x0CC8", "protocol": "RC5", "subdevice": "-1", "deviceName": "Video Projector", "device": "0", "key_name": "FULL", "company": "Marantz", "code_len": 28, "remoteName": "0_-1", "key_code": "126"},
{"pronto_code": "0x0000, 0x0073, 0x0000, 0x000C, 0x0040, 0x0020, 0x0020, 0x0020, 0x0020, 0x0020, 0x0020, 0x0020, 0x0020, 0x0020, 0x0020, 0x0020, 0x0020, 0x0040, 0x0020, 0x0020, 0x0020, 0x0020, 0x0020, 0x0020, 0x0020, 0x0020, 0x0040, 0x0CC8", "protocol": "RC5", "subdevice": "-1", "deviceName": "Video Projector", "device": "0", "key_name": "FULL (ASPECT)", "company": "Marantz", "code_len": 28, "remoteName": "0_-1", "key_code": "126"}
]