[
{"pronto_code": "0x0000, 0x0073, 0x0000, 0x000B, 0x0020, 0x0020, 0x0040, 0x0040, 0x0040, 0x0020, 0x0020, 0x0020, 0x0020, 0x0040, 0x0040, 0x0020, 0x0020, 0x0020, 0x0020, 0x0020, 0x0020, 0x0020, 0x0020, 0x0020, 0x0020, 0x0CC8", "protocol": "RC5", "subdevice": "-1", "deviceName": "Receiver", "device": "17", "key_name": "NUMBER 0 (TUNER) - R", "company": "Audio Control", "code_len": 26, "remoteName": "17_-1", "key_code": "0"},
{"pronto_code": "0x0000, 0x0073, 0x0000, 0x000B, 0x0020, 0x0020, 0x0040, 0x0040, 0x0040, 0x0020, 0x0020, 0x0020, 0x0020, 0x0040, 0x0040, 0x0020, 0x0020, 0x0020, 0x0020, 0x0020, 0x0020, 0x0020, 0x0020, 0x0040, 0x0020, 0x0CA8", "protocol": "RC5", "subdevice": "-1", "deviceName": "Receiver", "device": "17", "key_name": "NUMBER 1 (TUNER)", "company": "Audio Control", "code_len": 26, "remoteName": "17_-1", "key_code": "1"},
{"pronto_code": "0x0000, 0x0073, 0x0000, 0x000B, 0x0020, 0x0020, 0x0040, 0x0040, 0x0040, 0x0020, 0x0020, 0x0020, 0x0020, 0x0040, 0x0040, 0x0020, 0x0020, 0x0020, 0x0020, 0x0020, 0x0020, 0x0020, 0x0020, 0x0040, 0x0020, 0x0CA8", "protocol": "RC5", "subdevice": "-1", "deviceName": "Receiver", "device": "17", "key_name": "NUMBER 1 (TUNER) - R", "company": "Audio Control", "code_len": 26, "remoteName": "17_-1", "key_code": "1"},
{"pronto_code": "0x0000, 0x0073, 0x0000, 0x000A, 0x0020, 0x0020, 0x0040, 0x0040, 0x0040, 0x0020, 0x0020, 0x0020, 0x0020, 0x0040, 0x0040, 0x0020, 0x0020, 0x0020, 0x0020, 0x0020, 0x0020, 0x0040, 0x0040, 0x0CC8", "protocol": "RC5", "subdevice": "-1", "deviceName": "Receiver", "device": "17", "key_name": "NUMBER 2 (TUNER) - R", "company": "Audio Control", "code_len": 24, "remoteName": "17_-1", "key_code": "2"},
{"pronto_code": "0x0000, 0x0073, 0x0000, 0x000B, 0x0020, 0x0020, 0x0040, 0x0040, 0x0040, 0x0020, 0x0020, 0x0020, 0x0020, 0x0040, 0x0040, 0x0020, 0x0020, 0x0020, 0x0020, 0x0020, 0x0020, 0x0040, 0x0020, 0x0020, 0x0020, 0x0CA8", "protocol": "RC5", "subdevice": "-1", "deviceName": "Receiver", "device": "17", "key_name": "NUMBER 3 (TUNER) - R", "company": "Audio Control", "code_len": 26, "remoteName": "17_-1", "key_code": "3"},
{"pronto_code": "0x0000, 0x0073, 0x0000, 0x000A, 0x0020, 0x0020, 0x0040, 0x0040, 0x0040, 0x0020, 0x0020, 0x0020, 0x0020, 0x0040, 0x0040, 0x0020, 0x0020, 0x0020, 0x0020, 0x0040, 0x0040, 0x0020, 0x0020, 0x0CC8", "protocol": "RC5", "subdevice": "-1", "deviceName": "Receiver", "device": "17", "key_name": "NUMBER 4 (TUNER) - R", "company": "Audio Control", "code_len": 24, "remoteName": "17_-1", "key_code": "4"},
{"pronto_code": "0x0000, 0x0073, 0x0000, 0x000A, 0x0020, 0x0020, 0x0040, 0x0040, 0x0040, 0x0020, 0x0020, 0x0020, 0x0020, 0x0040, 0x0040, 0x0020, 0x0020, 0x0020, 0x0020, 0x0040, 0x0040, 0x0040, 0x0020, 0x0CA8", "protocol": "RC5", "subdevice": "-1", "deviceName": "Receiver", "device": "17", "key_name": "NUMBER 5 (TUNER) - R", "company": "Audio Control", "code_len": 24, "remoteName": "17_-1", "key_code": "5"},
{"pronto_code": "0x0000, 0x0073, 0x0000, 0x000A, 0x0020, 0x0020, 0x0040, 0x0040, 0x0040, 0x0020, 0x0020, 0x0020, 0x0020, 0x0040, 0x0040, 0x0020, 0x0020, 0x0020, 0x0020, 0x0040, 0x0020, 0x0020, 0x0040, 0x0CC8", "protocol": "RC5", "subdevice": "-1", "deviceName": "Receiver", "device": "17", "key_name": "NUMBER 6 (TUNER) - R", "company": "Audio Control", "code_len": 24, "remoteName": "17_-1", "key_code": "6"},
{"pronto_code": "0x0000, 0x0073, 0x0000, 0x000B, 0x0020, 0x0020, 0x0040, 0x0040, 0x0040, 0x0020, 0x0020, 0x0020, 0x0020, 0x0040, 0x0040, 0x0020, 0x0020, 0x0020, 0x0020, 0x0040, 0x0020, 0x0020, 0x0020, 0x0020, 0x0020, 0x0CA8", "protocol": "RC5", "subdevice": "-1", "deviceName": "Receiver", "device": "17", "key_name": "NUMBER 7 (TUNER) - R", "company": "Audio Control", "code_len": 26, "remoteName": "17_-1", "key_code": "7"},
{"pronto_code": "0x0000, 0x0073, 0x0000, 0x000A, 0x0020, 0x0020, 0x0040, 0x0040, 0x0040, 0x0020, 0x0020, 0x0020, 0x0020, 0x0040, 0x0040, 0x0020, 0x0020, 0x0040, 0x0040, 0x0020, 0x0020, 0x0020, 0x0020, 0x0CC8", "protocol": "RC5", "subdevice": "-1", "deviceName": "Receiver", "device": "17", "key_name": "NUMBER 8 (TUNER) - R", "company": "Audio Control", "code_len": 24, "remoteName": "17_-1", "key_code": "8"},
{"pronto_code": "0x0000, 0x0073, 0x0000, 0x000A, 0x0020, 0x0020, 0x0040, 0x0040, 0x0040, 0x0020, 0x0020, 0x0020, 0x0020, 0x0040, 0x0040, 0x0020, 0x0020, 0x0040, 0x0040, 0x0020, 0x0020, 0x0040, 0x0020, 0x0CA8", "protocol": "RC5", "subdevice": "-1", "deviceName": "Receiver", "device": "17", "key_name": "NUMBER 9 (TUNER) - R", "company": "Audio Control", "code_len": 24, "remoteName": "17_-1", "key_code": "9"},
{"pronto_code": "0x0000, 0x0073, 0x0000, 0x000B, 0x0020, 0x0020, 0x0040, 0x0040, 0x0040, 0x0020, 0x0020, 0x0020, 0x0020, 0x0040, 0x0020, 0x0020, 0x0040, 0x0020, 0x0020, 0x0020, 0x0020, 0x0020, 0x0020, 0x0020, 0x0020, 0x0CC8", "protocol": "RC5", "subdevice": "-1", "deviceName": "Receiver", "device": "17", "key_name": "PRE/SIRIUS + (T) - R", "company": "Audio Control", "code_len": 26, "remoteName": "17_-1", "key_code": "32"},
{"pronto_code": "0x0000, 0x0073, 0x0000, 0x000B, 0x0020, 0x0020, 0x0040, 0x0040, 0x0040, 0x0020, 0x0020, 0x0020, 0x0020, 0x0040, 0x0020, 0x0020, 0x0040, 0x0020, 0x0020, 0x0020, 0x0020, 0x0020, 0x0020, 0x0040, 0x0020, 0x0CA8", "protocol": "RC5", "subdevice": "-1", "deviceName": "Receiver", "device": "17", "key_name": "PRE/SIRIUS - (T) - R", "company": "Audio Control", "code_len": 26, "remoteName": "17_-1", "key_code": "33"},
{"pronto_code": "0x0000, 0x0073, 0x0000, 0x000A, 0x0020, 0x0020, 0x0040, 0x0040, 0x0040, 0x0020, 0x0020, 0x0020, 0x0020, 0x0040, 0x0020, 0x0020, 0x0040, 0x0020, 0x0020, 0x0040, 0x0040, 0x0040, 0x0020, 0x0CA8", "protocol": "RC5", "subdevice": "-1", "deviceName": "Receiver", "device": "17", "key_name": "PAGE DOWN (TUNE) - R", "company": "Audio Control", "code_len": 24, "remoteName": "17_-1", "key_code": "37"},
{"pronto_code": "0x0000, 0x0073, 0x0000, 0x000A, 0x0020, 0x0020, 0x0040, 0x0040, 0x0040, 0x0020, 0x0020, 0x0020, 0x0020, 0x0040, 0x0020, 0x0020, 0x0040, 0x0020, 0x0020, 0x0040, 0x0020, 0x0020, 0x0040, 0x0CC8", "protocol": "RC5", "subdevice": "-1", "deviceName": "Receiver", "device": "17", "key_name": "PAGE UP (TUNER) - R", "company": "Audio Control", "code_len": 24, "remoteName": "17_-1", "key_code": "38"},
{"pronto_code": "0x0000, 0x0073, 0x0000, 0x000A, 0x0020, 0x0020, 0x0040, 0x0040, 0x0040, 0x0020, 0x0020, 0x0020, 0x0020, 0x0040, 0x0020, 0x0020, 0x0040, 0x0040, 0x0040, 0x0020, 0x0020, 0x0040, 0x0020, 0x0CA8", "protocol": "RC5", "subdevice": "-1", "deviceName": "Receiver", "device": "17", "key_name": "DELETE PRESET - R", "company": "Audio Control", "code_len": 24, "remoteName": "17_-1", "key_code": "41"},
{"pronto_code": "0x0000, 0x0073, 0x0000, 0x000A, 0x0020, 0x0020, 0x0040, 0x0040, 0x0040, 0x0020, 0x0020, 0x0020, 0x0020, 0x0040, 0x0020, 0x0020, 0x0020, 0x0020, 0x0040, 0x0020, 0x0020, 0x0040, 0x0040, 0x0CC8", "protocol": "RC5", "subdevice": "-1", "deviceName": "Receiver", "device": "17", "key_name": "BAND (TUNER) - R", "company": "Audio Control", "code_len": 24, "remoteName": "17_-1", "key_code": "50"},
{"pronto_code": "0x0000, 0x0073, 0x0000, 0x000A, 0x0040, 0x0020, 0x0020, 0x0040, 0x0040, 0x0020, 0x0020, 0x0020, 0x0020, 0x0040, 0x0040, 0x0020, 0x0020, 0x0040, 0x0020, 0x0020, 0x0040, 0x0040, 0x0020, 0x0CA8", "protocol": "RC5", "subdevice": "-1", "deviceName": "Receiver", "device": "17", "key_name": "TUNING + RIGHT - R", "company": "Audio Control", "code_len": 24, "remoteName": "17_-1", "key_code": "77"},
{"pronto_code": "0x0000, 0x0073, 0x0000, 0x000A, 0x0040, 0x0020, 0x0020, 0x0040, 0x0040, 0x0020, 0x0020, 0x0020, 0x0020, 0x0040, 0x0040, 0x0020, 0x0020, 0x0040, 0x0020, 0x0020, 0x0020, 0x0020, 0x0040, 0x0CC8", "protocol": "RC5", "subdevice": "-1", "deviceName": "Receiver", "device": "17", "key_name": "TUNING - LEFT - R", "company": "Audio Control", "code_len": 24, "remoteName": "17_-1", "key_code": "78"},
{"pronto_code": "0x0000, 0x0073, 0x0000, 0x0009, 0x0040, 0x0020, 0x0020, 0x0040, 0x0040, 0x0020, 0x0020, 0x0020, 0x0020, 0x0040, 0x0040, 0x0040, 0x0040, 0x0040, 0x0040, 0x0040, 0x0020, 0x0CA8", "protocol": "RC5", "subdevice": "-1", "deviceName": "Receiver", "device": "17", "key_name": "PRESET DOWN (TUN - R", "company": "Audio Control", "code_len": 22, "remoteName": "17_-1", "key_code": "85"},
{"pronto_code": "0x0000, 0x0073, 0x0000, 0x0009, 0x0040, 0x0020, 0x0020, 0x0040, 0x0040, 0x0020, 0x0020, 0x0020, 0x0020, 0x0040, 0x0040, 0x0040, 0x0040, 0x0040, 0x0020, 0x0020, 0x0040, 0x0CC8", "protocol": "RC5", "subdevice": "-1", "deviceName": "Receiver", "device": "17", "key_name": "PRESET UP (TUNE) - R", "company": "Audio Control", "code_len": 22, "remoteName": "17_-1", "key_code": "86"}
]