[
{"pronto_code": "0x0000, 0x006D, 0x0000, 0x000C, 0x001B, 0x0120, 0x001B, 0x00C0, 0x001B, 0x00C0, 0x001B, 0x00C0, 0x001B, 0x0120, 0x001B, 0x00C0, 0x001B, 0x00C0, 0x001B, 0x00C0, 0x001B, 0x00C0, 0x001B, 0x00C0, 0x001B, 0x00C0, 0x0000, 0x082A", "protocol": "Velleman", "subdevice": "-1", "deviceName": "HD", "device": "1", "key_name": "ON 0", "company": "Elan", "code_len": 28, "remoteName": "1_-1", "key_code": "0"},
{"pronto_code": "0x0000, 0x006D, 0x0000, 0x000C, 0x001B, 0x0120, 0x001B, 0x00C0, 0x001B, 0x00C0, 0x001B, 0x00C0, 0x001B, 0x0120, 0x001B, 0x00C0, 0x001B, 0x00C0, 0x001B, 0x00C0, 0x001B, 0x00C0, 0x001B, 0x00C0, 0x001B, 0x0120, 0x0000, 0x082A", "protocol": "Velleman", "subdevice": "-1", "deviceName": "HD", "device": "1", "key_name": "ON 1", "company": "Elan", "code_len": 28, "remoteName": "1_-1", "key_code": "1"},
{"pronto_code": "0x0000, 0x006D, 0x0000, 0x000C, 0x001B, 0x0120, 0x001B, 0x00C0, 0x001B, 0x00C0, 0x001B, 0x00C0, 0x001B, 0x0120, 0x001B, 0x00C0, 0x001B, 0x00C0, 0x001B, 0x00C0, 0x001B, 0x00C0, 0x001B, 0x0120, 0x001B, 0x00C0, 0x0000, 0x082A", "protocol": "Velleman", "subdevice": "-1", "deviceName": "HD", "device": "1", "key_name": "ON 2", "company": "Elan", "code_len": 28, "remoteName": "1_-1", "key_code": "2"},
{"pronto_code": "0x0000, 0x006D, 0x0000, 0x000C, 0x001B, 0x0120, 0x001B, 0x00C0, 0x001B, 0x00C0, 0x001B, 0x00C0, 0x001B, 0x0120, 0x001B, 0x00C0, 0x001B, 0x00C0, 0x001B, 0x00C0, 0x001B, 0x00C0, 0x001B, 0x0120, 0x001B, 0x0120, 0x0000, 0x082A", "protocol": "Velleman", "subdevice": "-1", "deviceName": "HD", "device": "1", "key_name": "ON 3", "company": "Elan", "code_len": 28, "remoteName": "1_-1", "key_code": "3"},
{"pronto_code": "0x0000, 0x006D, 0x0000, 0x000C, 0x001B, 0x0120, 0x001B, 0x00C0, 0x001B, 0x00C0, 0x001B, 0x00C0, 0x001B, 0x0120, 0x001B, 0x00C0, 0x001B, 0x00C0, 0x001B, 0x00C0, 0x001B, 0x0120, 0x001B, 0x00C0, 0x001B, 0x00C0, 0x0000, 0x082A", "protocol": "Velleman", "subdevice": "-1", "deviceName": "HD", "device": "1", "key_name": "ON 4", "company": "Elan", "code_len": 28, "remoteName": "1_-1", "key_code": "4"},
{"pronto_code": "0x0000, 0x006D, 0x0000, 0x000C, 0x001B, 0x0120, 0x001B, 0x00C0, 0x001B, 0x00C0, 0x001B, 0x00C0, 0x001B, 0x0120, 0x001B, 0x00C0, 0x001B, 0x00C0, 0x001B, 0x00C0, 0x001B, 0x0120, 0x001B, 0x00C0, 0x001B, 0x0120, 0x0000, 0x082A", "protocol": "Velleman", "subdevice": "-1", "deviceName": "HD", "device": "1", "key_name": "ON 5", "company": "Elan", "code_len": 28, "remoteName": "1_-1", "key_code": "5"},
{"pronto_code": "0x0000, 0x006D, 0x0000, 0x000C, 0x001B, 0x0120, 0x001B, 0x00C0, 0x001B, 0x00C0, 0x001B, 0x00C0, 0x001B, 0x0120, 0x001B, 0x00C0, 0x001B, 0x00C0, 0x001B, 0x00C0, 0x001B, 0x0120, 0x001B, 0x0120, 0x001B, 0x00C0, 0x0000, 0x082A", "protocol": "Velleman", "subdevice": "-1", "deviceName": "HD", "device": "1", "key_name": "ON 6", "company": "Elan", "code_len": 28, "remoteName": "1_-1", "key_code": "6"},
{"pronto_code": "0x0000, 0x006D, 0x0000, 0x000C, 0x001B, 0x0120, 0x001B, 0x00C0, 0x001B, 0x00C0, 0x001B, 0x00C0, 0x001B, 0x0120, 0x001B, 0x00C0, 0x001B, 0x00C0, 0x001B, 0x00C0, 0x001B, 0x0120, 0x001B, 0x0120, 0x001B, 0x0120, 0x0000, 0x082A", "protocol": "Velleman", "subdevice": "-1", "deviceName": "HD", "device": "1", "key_name": "ON 7", "company": "Elan", "code_len": 28, "remoteName": "1_-1", "key_code": "7"},
{"pronto_code": "0x0000, 0x006D, 0x0000, 0x000C, 0x001B, 0x0120, 0x001B, 0x00C0, 0x001B, 0x00C0, 0x001B, 0x00C0, 0x001B, 0x0120, 0x001B, 0x00C0, 0x001B, 0x00C0, 0x001B, 0x0120, 0x001B, 0x00C0, 0x001B, 0x00C0, 0x001B, 0x00C0, 0x0000, 0x082A", "protocol": "Velleman", "subdevice": "-1", "deviceName": "HD", "device": "1", "key_name": "ON 8", "company": "Elan", "code_len": 28, "remoteName": "1_-1", "key_code": "8"},
{"pronto_code": "0x0000, 0x006D, 0x0000, 0x000C, 0x001B, 0x0120, 0x001B, 0x00C0, 0x001B, 0x00C0, 0x001B, 0x00C0, 0x001B, 0x0120, 0x001B, 0x00C0, 0x001B, 0x00C0, 0x001B, 0x0120, 0x001B, 0x00C0, 0x001B, 0x00C0, 0x001B, 0x0120, 0x0000, 0x082A", "protocol": "Velleman", "subdevice": "-1", "deviceName": "HD", "device": "1", "key_name": "ON 9", "company": "Elan", "code_len": 28, "remoteName": "1_-1", "key_code": "9"},
{"pronto_code": "0x0000, 0x006D, 0x0000, 0x000C, 0x001B, 0x0120, 0x001B, 0x00C0, 0x001B, 0x00C0, 0x001B, 0x00C0, 0x001B, 0x0120, 0x001B, 0x00C0, 0x001B, 0x00C0, 0x001B, 0x0120, 0x001B, 0x00C0, 0x001B, 0x0120, 0x001B, 0x00C0, 0x0000, 0x082A", "protocol": "Velleman", "subdevice": "-1", "deviceName": "HD", "device": "1", "key_name": "ON A", "company": "Elan", "code_len": 28, "remoteName": "1_-1", "key_code": "10"},
{"pronto_code": "0x0000, 0x006D, 0x0000, 0x000C, 0x001B, 0x0120, 0x001B, 0x00C0, 0x001B, 0x00C0, 0x001B, 0x00C0, 0x001B, 0x0120, 0x001B, 0x00C0, 0x001B, 0x00C0, 0x001B, 0x0120, 0x001B, 0x00C0, 0x001B, 0x0120, 0x001B, 0x0120, 0x0000, 0x082A", "protocol": "Velleman", "subdevice": "-1", "deviceName": "HD", "device": "1", "key_name": "ON B", "company": "Elan", "code_len": 28, "remoteName": "1_-1", "key_code": "11"},
{"pronto_code": "0x0000, 0x006D, 0x0000, 0x000C, 0x001B, 0x0120, 0x001B, 0x00C0, 0x001B, 0x00C0, 0x001B, 0x00C0, 0x001B, 0x0120, 0x001B, 0x00C0, 0x001B, 0x00C0, 0x001B, 0x0120, 0x001B, 0x0120, 0x001B, 0x00C0, 0x001B, 0x00C0, 0x0000, 0x082A", "protocol": "Velleman", "subdevice": "-1", "deviceName": "HD", "device": "1", "key_name": "ON C", "company": "Elan", "code_len": 28, "remoteName": "1_-1", "key_code": "12"},
{"pronto_code": "0x0000, 0x006D, 0x0000, 0x000C, 0x001B, 0x0120, 0x001B, 0x00C0, 0x001B, 0x00C0, 0x001B, 0x00C0, 0x001B, 0x0120, 0x001B, 0x00C0, 0x001B, 0x00C0, 0x001B, 0x0120, 0x001B, 0x0120, 0x001B, 0x00C0, 0x001B, 0x0120, 0x0000, 0x082A", "protocol": "Velleman", "subdevice": "-1", "deviceName": "HD", "device": "1", "key_name": "ON D", "company": "Elan", "code_len": 28, "remoteName": "1_-1", "key_code": "13"},
{"pronto_code": "0x0000, 0x006D, 0x0000, 0x000C, 0x001B, 0x0120, 0x001B, 0x00C0, 0x001B, 0x00C0, 0x001B, 0x00C0, 0x001B, 0x0120, 0x001B, 0x00C0, 0x001B, 0x00C0, 0x001B, 0x0120, 0x001B, 0x0120, 0x001B, 0x0120, 0x001B, 0x00C0, 0x0000, 0x082A", "protocol": "Velleman", "subdevice": "-1", "deviceName": "HD", "device": "1", "key_name": "ON E", "company": "Elan", "code_len": 28, "remoteName": "1_-1", "key_code": "14"},
{"pronto_code": "0x0000, 0x006D, 0x0000, 0x000C, 0x001B, 0x0120, 0x001B, 0x00C0, 0x001B, 0x00C0, 0x001B, 0x00C0, 0x001B, 0x0120, 0x001B, 0x00C0, 0x001B, 0x00C0, 0x001B, 0x0120, 0x001B, 0x0120, 0x001B, 0x0120, 0x001B, 0x0120, 0x0000, 0x082A", "protocol": "Velleman", "subdevice": "-1", "deviceName": "HD", "device": "1", "key_name": "ON F", "company": "Elan", "code_len": 28, "remoteName": "1_-1", "key_code": "15"},
{"pronto_code": "0x0000, 0x006D, 0x0000, 0x000C, 0x001B, 0x0120, 0x001B, 0x00C0, 0x001B, 0x00C0, 0x001B, 0x00C0, 0x001B, 0x0120, 0x001B, 0x00C0, 0x001B, 0x0120, 0x001B, 0x00C0, 0x001B, 0x00C0, 0x001B, 0x00C0, 0x001B, 0x00C0, 0x0000, 0x082A", "protocol": "Velleman", "subdevice": "-1", "deviceName": "HD", "device": "1", "key_name": "ON G", "company": "Elan", "code_len": 28, "remoteName": "1_-1", "key_code": "16"},
{"pronto_code": "0x0000, 0x006D, 0x0000, 0x000C, 0x001B, 0x0120, 0x001B, 0x00C0, 0x001B, 0x00C0, 0x001B, 0x00C0, 0x001B, 0x0120, 0x001B, 0x00C0, 0x001B, 0x0120, 0x001B, 0x00C0, 0x001B, 0x00C0, 0x001B, 0x00C0, 0x001B, 0x0120, 0x0000, 0x082A", "protocol": "Velleman", "subdevice": "-1", "deviceName": "HD", "device": "1", "key_name": "WH ON", "company": "Elan", "code_len": 28, "remoteName": "1_-1", "key_code": "17"},
{"pronto_code": "0x0000, 0x006D, 0x0000, 0x000C, 0x001B, 0x0120, 0x001B, 0x00C0, 0x001B, 0x00C0, 0x001B, 0x00C0, 0x001B, 0x0120, 0x001B, 0x00C0, 0x001B, 0x0120, 0x001B, 0x00C0, 0x001B, 0x00C0, 0x001B, 0x00C0, 0x001B, 0x0120, 0x0000, 0x082A", "protocol": "Velleman", "subdevice": "-1", "deviceName": "HD", "device": "1", "key_name": "ON H", "company": "Elan", "code_len": 28, "remoteName": "1_-1", "key_code": "17"},
{"pronto_code": "0x0000, 0x006D, 0x0000, 0x000C, 0x001B, 0x0120, 0x001B, 0x00C0, 0x001B, 0x00C0, 0x001B, 0x00C0, 0x001B, 0x0120, 0x001B, 0x00C0, 0x001B, 0x0120, 0x001B, 0x00C0, 0x001B, 0x00C0, 0x001B, 0x0120, 0x001B, 0x00C0, 0x0000, 0x082A", "protocol": "Velleman", "subdevice": "-1", "deviceName": "HD", "device": "1", "key_name": "ON I", "company": "Elan", "code_len": 28, "remoteName": "1_-1", "key_code": "18"},
{"pronto_code": "0x0000, 0x006D, 0x0000, 0x000C, 0x001B, 0x0120, 0x001B, 0x00C0, 0x001B, 0x00C0, 0x001B, 0x00C0, 0x001B, 0x0120, 0x001B, 0x00C0, 0x001B, 0x0120, 0x001B, 0x00C0, 0x001B, 0x00C0, 0x001B, 0x0120, 0x001B, 0x0120, 0x0000, 0x082A", "protocol": "Velleman", "subdevice": "-1", "deviceName": "HD", "device": "1", "key_name": "ON J", "company": "Elan", "code_len": 28, "remoteName": "1_-1", "key_code": "19"},
{"pronto_code": "0x0000, 0x006D, 0x0000, 0x000C, 0x001B, 0x0120, 0x001B, 0x00C0, 0x001B, 0x00C0, 0x001B, 0x00C0, 0x001B, 0x0120, 0x001B, 0x00C0, 0x001B, 0x0120, 0x001B, 0x0120, 0x001B, 0x00C0, 0x001B, 0x00C0, 0x001B, 0x00C0, 0x0000, 0x082A", "protocol": "Velleman", "subdevice": "-1", "deviceName": "HD", "device": "1", "key_name": "ON ELAN", "company": "Elan", "code_len": 28, "remoteName": "1_-1", "key_code": "24"},
{"pronto_code": "0x0000, 0x006D, 0x0000, 0x000C, 0x001B, 0x0120, 0x001B, 0x00C0, 0x001B, 0x00C0, 0x001B, 0x00C0, 0x001B, 0x0120, 0x001B, 0x00C0, 0x001B, 0x0120, 0x001B, 0x0120, 0x001B, 0x00C0, 0x001B, 0x00C0, 0x001B, 0x0120, 0x0000, 0x082A", "protocol": "Velleman", "subdevice": "-1", "deviceName": "HD", "device": "1", "key_name": "ON POWER", "company": "Elan", "code_len": 28, "remoteName": "1_-1", "key_code": "25"},
{"pronto_code": "0x0000, 0x006D, 0x0000, 0x000C, 0x001B, 0x0120, 0x001B, 0x00C0, 0x001B, 0x00C0, 0x001B, 0x00C0, 0x001B, 0x0120, 0x001B, 0x00C0, 0x001B, 0x0120, 0x001B, 0x0120, 0x001B, 0x00C0, 0x001B, 0x0120, 0x001B, 0x00C0, 0x0000, 0x082A", "protocol": "Velleman", "subdevice": "-1", "deviceName": "HD", "device": "1", "key_name": "ON MUTE", "company": "Elan", "code_len": 28, "remoteName": "1_-1", "key_code": "26"},
{"pronto_code": "0x0000, 0x006D, 0x0000, 0x000C, 0x001B, 0x0120, 0x001B, 0x00C0, 0x001B, 0x00C0, 0x001B, 0x00C0, 0x001B, 0x0120, 0x001B, 0x00C0, 0x001B, 0x0120, 0x001B, 0x0120, 0x001B, 0x00C0, 0x001B, 0x0120, 0x001B, 0x0120, 0x0000, 0x082A", "protocol": "Velleman", "subdevice": "-1", "deviceName": "HD", "device": "1", "key_name": "ON DND", "company": "Elan", "code_len": 28, "remoteName": "1_-1", "key_code": "27"},
{"pronto_code": "0x0000, 0x006D, 0x0000, 0x000C, 0x001B, 0x0120, 0x001B, 0x00C0, 0x001B, 0x00C0, 0x001B, 0x00C0, 0x001B, 0x0120, 0x001B, 0x00C0, 0x001B, 0x0120, 0x001B, 0x0120, 0x001B, 0x00C0, 0x001B, 0x0120, 0x001B, 0x0120, 0x0000, 0x082A", "protocol": "Velleman", "subdevice": "-1", "deviceName": "HD", "device": "1", "key_name": "OFF 0", "company": "Elan", "code_len": 0, "remoteName": "1_-1", "key_code": "32"},
{"pronto_code": "0x0000, 0x006D, 0x0000, 0x000C, 0x001B, 0x0120, 0x001B, 0x00C0, 0x001B, 0x00C0, 0x001B, 0x00C0, 0x001B, 0x0120, 0x001B, 0x00C0, 0x001B, 0x0120, 0x001B, 0x0120, 0x001B, 0x00C0, 0x001B, 0x0120, 0x001B, 0x0120, 0x0000, 0x082A", "protocol": "Velleman", "subdevice": "-1", "deviceName": "HD", "device": "1", "key_name": "OFF 1", "company": "Elan", "code_len": 0, "remoteName": "1_-1", "key_code": "33"},
{"pronto_code": "0x0000, 0x006D, 0x0000, 0x000C, 0x001B, 0x0120, 0x001B, 0x00C0, 0x001B, 0x00C0, 0x001B, 0x00C0, 0x001B, 0x0120, 0x001B, 0x00C0, 0x001B, 0x0120, 0x001B, 0x0120, 0x001B, 0x00C0, 0x001B, 0x0120, 0x001B, 0x0120, 0x0000, 0x082A", "protocol": "Velleman", "subdevice": "-1", "deviceName": "HD", "device": "1", "key_name": "OFF 2", "company": "Elan", "code_len": 0, "remoteName": "1_-1", "key_code": "34"},
{"pronto_code": "0x0000, 0x006D, 0x0000, 0x000C, 0x001B, 0x0120, 0x001B, 0x00C0, 0x001B, 0x00C0, 0x001B, 0x00C0, 0x001B, 0x0120, 0x001B, 0x00C0, 0x001B, 0x0120, 0x001B, 0x0120, 0x001B, 0x00C0, 0x001B, 0x0120, 0x001B, 0x0120, 0x0000, 0x082A", "protocol": "Velleman", "subdevice": "-1", "deviceName": "HD", "device": "1", "key_name": "OFF 3", "company": "Elan", "code_len": 0, "remoteName": "1_-1", "key_code": "35"},
{"pronto_code": "0x0000, 0x006D, 0x0000, 0x000C, 0x001B, 0x0120, 0x001B, 0x00C0, 0x001B, 0x00C0, 0x001B, 0x00C0, 0x001B, 0x0120, 0x001B, 0x00C0, 0x001B, 0x0120, 0x001B, 0x0120, 0x001B, 0x00C0, 0x001B, 0x0120, 0x001B, 0x0120, 0x0000, 0x082A", "protocol": "Velleman", "subdevice": "-1", "deviceName": "HD", "device": "1", "key_name": "OFF 4", "company": "Elan", "code_len": 0, "remoteName": "1_-1", "key_code": "36"},
{"pronto_code": "0x0000, 0x006D, 0x0000, 0x000C, 0x001B, 0x0120, 0x001B, 0x00C0, 0x001B, 0x00C0, 0x001B, 0x00C0, 0x001B, 0x0120, 0x001B, 0x00C0, 0x001B, 0x0120, 0x001B, 0x0120, 0x001B, 0x00C0, 0x001B, 0x0120, 0x001B, 0x0120, 0x0000, 0x082A", "protocol": "Velleman", "subdevice": "-1", "deviceName": "HD", "device": "1", "key_name": "OFF 5", "company": "Elan", "code_len": 0, "remoteName": "1_-1", "key_code": "37"},
{"pronto_code": "0x0000, 0x006D, 0x0000, 0x000C, 0x001B, 0x0120, 0x001B, 0x00C0, 0x001B, 0x00C0, 0x001B, 0x00C0, 0x001B, 0x0120, 0x001B, 0x00C0, 0x001B, 0x0120, 0x001B, 0x0120, 0x001B, 0x00C0, 0x001B, 0x0120, 0x001B, 0x0120, 0x0000, 0x082A", "protocol": "Velleman", "subdevice": "-1", "deviceName": "HD", "device": "1", "key_name": "OFF 6", "company": "Elan", "code_len": 0, "remoteName": "1_-1", "key_code": "38"},
{"pronto_code": "0x0000, 0x006D, 0x0000, 0x000C, 0x001B, 0x0120, 0x001B, 0x00C0, 0x001B, 0x00C0, 0x001B, 0x00C0, 0x001B, 0x0120, 0x001B, 0x00C0, 0x001B, 0x0120, 0x001B, 0x0120, 0x001B, 0x00C0, 0x001B, 0x0120, 0x001B, 0x0120, 0x0000, 0x082A", "protocol": "Velleman", "subdevice": "-1", "deviceName": "HD", "device": "1", "key_name": "OFF 7", "company": "Elan", "code_len": 0, "remoteName": "1_-1", "key_code": "39"},
{"pronto_code": "0x0000, 0x006D, 0x0000, 0x000C, 0x001B, 0x0120, 0x001B, 0x00C0, 0x001B, 0x00C0, 0x001B, 0x00C0, 0x001B, 0x0120, 0x001B, 0x00C0, 0x001B, 0x0120, 0x001B, 0x0120, 0x001B, 0x00C0, 0x001B, 0x0120, 0x001B, 0x0120, 0x0000, 0x082A", "protocol": "Velleman", "subdevice": "-1", "deviceName": "HD", "device": "1", "key_name": "OFF 8", "company": "Elan", "code_len": 0, "remoteName": "1_-1", "key_code": "40"},
{"pronto_code": "0x0000, 0x006D, 0x0000, 0x000C, 0x001B, 0x0120, 0x001B, 0x00C0, 0x001B, 0x00C0, 0x001B, 0x00C0, 0x001B, 0x0120, 0x001B, 0x00C0, 0x001B, 0x0120, 0x001B, 0x0120, 0x001B, 0x00C0, 0x001B, 0x0120, 0x001B, 0x0120, 0x0000, 0x082A", "protocol": "Velleman", "subdevice": "-1", "deviceName": "HD", "device": "1", "key_name": "OFF 9", "company": "Elan", "code_len": 0, "remoteName": "1_-1", "key_code": "41"},
{"pronto_code": "0x0000, 0x006D, 0x0000, 0x000C, 0x001B, 0x0120, 0x001B, 0x00C0, 0x001B, 0x00C0, 0x001B, 0x00C0, 0x001B, 0x0120, 0x001B, 0x00C0, 0x001B, 0x0120, 0x001B, 0x0120, 0x001B, 0x00C0, 0x001B, 0x0120, 0x001B, 0x0120, 0x0000, 0x082A", "protocol": "Velleman", "subdevice": "-1", "deviceName": "HD", "device": "1", "key_name": "OFF A", "company": "Elan", "code_len": 0, "remoteName": "1_-1", "key_code": "42"},
{"pronto_code": "0x0000, 0x006D, 0x0000, 0x000C, 0x001B, 0x0120, 0x001B, 0x00C0, 0x001B, 0x00C0, 0x001B, 0x00C0, 0x001B, 0x0120, 0x001B, 0x00C0, 0x001B, 0x0120, 0x001B, 0x0120, 0x001B, 0x00C0, 0x001B, 0x0120, 0x001B, 0x0120, 0x0000, 0x082A", "protocol": "Velleman", "subdevice": "-1", "deviceName": "HD", "device": "1", "key_name": "OFF B", "company": "Elan", "code_len": 0, "remoteName": "1_-1", "key_code": "43"},
{"pronto_code": "0x0000, 0x006D, 0x0000, 0x000C, 0x001B, 0x0120, 0x001B, 0x00C0, 0x001B, 0x00C0, 0x001B, 0x00C0, 0x001B, 0x0120, 0x001B, 0x00C0, 0x001B, 0x0120, 0x001B, 0x0120, 0x001B, 0x00C0, 0x001B, 0x0120, 0x001B, 0x0120, 0x0000, 0x082A", "protocol": "Velleman", "subdevice": "-1", "deviceName": "HD", "device": "1", "key_name": "OFF C", "company": "Elan", "code_len": 0, "remoteName": "1_-1", "key_code": "44"},
{"pronto_code": "0x0000, 0x006D, 0x0000, 0x000C, 0x001B, 0x0120, 0x001B, 0x00C0, 0x001B, 0x00C0, 0x001B, 0x00C0, 0x001B, 0x0120, 0x001B, 0x00C0, 0x001B, 0x0120, 0x001B, 0x0120, 0x001B, 0x00C0, 0x001B, 0x0120, 0x001B, 0x0120, 0x0000, 0x082A", "protocol": "Velleman", "subdevice": "-1", "deviceName": "HD", "device": "1", "key_name": "OFF D", "company": "Elan", "code_len": 0, "remoteName": "1_-1", "key_code": "45"},
{"pronto_code": "0x0000, 0x006D, 0x0000, 0x000C, 0x001B, 0x0120, 0x001B, 0x00C0, 0x001B, 0x00C0, 0x001B, 0x00C0, 0x001B, 0x0120, 0x001B, 0x00C0, 0x001B, 0x0120, 0x001B, 0x0120, 0x001B, 0x00C0, 0x001B, 0x0120, 0x001B, 0x0120, 0x0000, 0x082A", "protocol": "Velleman", "subdevice": "-1", "deviceName": "HD", "device": "1", "key_name": "OFF E", "company": "Elan", "code_len": 0, "remoteName": "1_-1", "key_code": "46"},
{"pronto_code": "0x0000, 0x006D, 0x0000, 0x000C, 0x001B, 0x0120, 0x001B, 0x00C0, 0x001B, 0x00C0, 0x001B, 0x00C0, 0x001B, 0x0120, 0x001B, 0x00C0, 0x001B, 0x0120, 0x001B, 0x0120, 0x001B, 0x00C0, 0x001B, 0x0120, 0x001B, 0x0120, 0x0000, 0x082A", "protocol": "Velleman", "subdevice": "-1", "deviceName": "HD", "device": "1", "key_name": "OFF F", "company": "Elan", "code_len": 0, "remoteName": "1_-1", "key_code": "47"},
{"pronto_code": "0x0000, 0x006D, 0x0000, 0x000C, 0x001B, 0x0120, 0x001B, 0x00C0, 0x001B, 0x00C0, 0x001B, 0x00C0, 0x001B, 0x0120, 0x001B, 0x00C0, 0x001B, 0x0120, 0x001B, 0x0120, 0x001B, 0x00C0, 0x001B, 0x0120, 0x001B, 0x0120, 0x0000, 0x082A", "protocol": "Velleman", "subdevice": "-1", "deviceName": "HD", "device": "1", "key_name": "OFF G", "company": "Elan", "code_len": 0, "remoteName": "1_-1", "key_code": "48"},
{"pronto_code": "0x0000, 0x006D, 0x0000, 0x000C, 0x001B, 0x0120, 0x001B, 0x00C0, 0x001B, 0x00C0, 0x001B, 0x00C0, 0x001B, 0x0120, 0x001B, 0x00C0, 0x001B, 0x0120, 0x001B, 0x0120, 0x001B, 0x00C0, 0x001B, 0x0120, 0x001B, 0x0120, 0x0000, 0x082A", "protocol": "Velleman", "subdevice": "-1", "deviceName": "HD", "device": "1", "key_name": "WH OFF", "company": "Elan", "code_len": 0, "remoteName": "1_-1", "key_code": "49"},
{"pronto_code": "0x0000, 0x006D, 0x0000, 0x000C, 0x001B, 0x0120, 0x001B, 0x00C0, 0x001B, 0x00C0, 0x001B, 0x00C0, 0x001B, 0x0120, 0x001B, 0x00C0, 0x001B, 0x0120, 0x001B, 0x0120, 0x001B, 0x00C0, 0x001B, 0x0120, 0x001B, 0x0120, 0x0000, 0x082A", "protocol": "Velleman", "subdevice": "-1", "deviceName": "HD", "device": "1", "key_name": "", "company": "Elan", "code_len": 0, "remoteName": "1_-1", "key_code": "49"},
{"pronto_code": "0x0000, 0x006D, 0x0000, 0x000C, 0x001B, 0x0120, 0x001B, 0x00C0, 0x001B, 0x00C0, 0x001B, 0x00C0, 0x001B, 0x0120, 0x001B, 0x00C0, 0x001B, 0x0120, 0x001B, 0x0120, 0x001B, 0x00C0, 0x001B, 0x0120, 0x001B, 0x0120, 0x0000, 0x082A", "protocol": "Velleman", "subdevice": "-1", "deviceName": "HD", "device": "1", "key_name": "OFF H", "company": "Elan", "code_len": 0, "remoteName": "1_-1", "key_code": "49"},
{"pronto_code": "0x0000, 0x006D, 0x0000, 0x000C, 0x001B, 0x0120, 0x001B, 0x00C0, 0x001B, 0x00C0, 0x001B, 0x00C0, 0x001B, 0x0120, 0x001B, 0x00C0, 0x001B, 0x0120, 0x001B, 0x0120, 0x001B, 0x00C0, 0x001B, 0x0120, 0x001B, 0x0120, 0x0000, 0x082A", "protocol": "Velleman", "subdevice": "-1", "deviceName": "HD", "device": "1", "key_name": "OFF I", "company": "Elan", "code_len": 0, "remoteName": "1_-1", "key_code": "50"},
{"pronto_code": "0x0000, 0x006D, 0x0000, 0x000C, 0x001B, 0x0120, 0x001B, 0x00C0, 0x001B, 0x00C0, 0x001B, 0x00C0, 0x001B, 0x0120, 0x001B, 0x00C0, 0x001B, 0x0120, 0x001B, 0x0120, 0x001B, 0x00C0, 0x001B, 0x0120, 0x001B, 0x0120, 0x0000, 0x082A", "protocol": "Velleman", "subdevice": "-1", "deviceName": "HD", "device": "1", "key_name": "OFF J", "company": "Elan", "code_len": 0, "remoteName": "1_-1", "key_code": "51"},
{"pronto_code": "0x0000, 0x006D, 0x0000, 0x000C, 0x001B, 0x0120, 0x001B, 0x00C0, 0x001B, 0x00C0, 0x001B, 0x00C0, 0x001B, 0x0120, 0x001B, 0x00C0, 0x001B, 0x0120, 0x001B, 0x0120, 0x001B, 0x00C0, 0x001B, 0x0120, 0x001B, 0x0120, 0x0000, 0x082A", "protocol": "Velleman", "subdevice": "-1", "deviceName": "HD", "device": "1", "key_name": "OFF ELAN", "company": "Elan", "code_len": 0, "remoteName": "1_-1", "key_code": "56"},
{"pronto_code": "0x0000, 0x006D, 0x0000, 0x000C, 0x001B, 0x0120, 0x001B, 0x00C0, 0x001B, 0x00C0, 0x001B, 0x00C0, 0x001B, 0x0120, 0x001B, 0x00C0, 0x001B, 0x0120, 0x001B, 0x0120, 0x001B, 0x00C0, 0x001B, 0x0120, 0x001B, 0x0120, 0x0000, 0x082A", "protocol": "Velleman", "subdevice": "-1", "deviceName": "HD", "device": "1", "key_name": "OFF PWR", "company": "Elan", "code_len": 0, "remoteName": "1_-1", "key_code": "57"},
{"pronto_code": "0x0000, 0x006D, 0x0000, 0x000C, 0x001B, 0x0120, 0x001B, 0x00C0, 0x001B, 0x00C0, 0x001B, 0x00C0, 0x001B, 0x0120, 0x001B, 0x00C0, 0x001B, 0x0120, 0x001B, 0x0120, 0x001B, 0x00C0, 0x001B, 0x0120, 0x001B, 0x0120, 0x0000, 0x082A", "protocol": "Velleman", "subdevice": "-1", "deviceName": "HD", "device": "1", "key_name": "OFF MUTE", "company": "Elan", "code_len": 0, "remoteName": "1_-1", "key_code": "58"},
{"pronto_code": "0x0000, 0x006D, 0x0000, 0x000C, 0x001B, 0x0120, 0x001B, 0x00C0, 0x001B, 0x00C0, 0x001B, 0x00C0, 0x001B, 0x0120, 0x001B, 0x00C0, 0x001B, 0x0120, 0x001B, 0x0120, 0x001B, 0x00C0, 0x001B, 0x0120, 0x001B, 0x0120, 0x0000, 0x082A", "protocol": "Velleman", "subdevice": "-1", "deviceName": "HD", "device": "1", "key_name": "OFF DND", "company": "Elan", "code_len": 0, "remoteName": "1_-1", "key_code": "59"}
]