[
{"pronto_code": "0x0000, 0x0073, 0x0000, 0x000C, 0x0020, 0x0020, 0x0040, 0x0040, 0x0040, 0x0020, 0x0020, 0x0020, 0x0020, 0x0020, 0x0020, 0x0020, 0x0020, 0x0020, 0x0020, 0x0020, 0x0020, 0x0020, 0x0020, 0x0020, 0x0020, 0x0020, 0x0020, 0x0CC8", "protocol": "RC5", "subdevice": "-1", "deviceName": "Surround Receiver", "device": "16", "key_name": "SAT A", "company": "Arcam", "code_len": 28, "remoteName": "16_-1", "key_code": "0"},
{"pronto_code": "0x0000, 0x0073, 0x0000, 0x000C, 0x0020, 0x0020, 0x0040, 0x0040, 0x0040, 0x0020, 0x0020, 0x0020, 0x0020, 0x0020, 0x0020, 0x0020, 0x0020, 0x0020, 0x0020, 0x0020, 0x0020, 0x0020, 0x0020, 0x0020, 0x0020, 0x0020, 0x0020, 0x0CC8", "protocol": "RC5", "subdevice": "-1", "deviceName": "Surround Receiver", "device": "16", "key_name": "SAT B", "company": "Arcam", "code_len": 28, "remoteName": "16_-1", "key_code": "0"},
{"pronto_code": "0x0000, 0x0073, 0x0000, 0x000C, 0x0020, 0x0020, 0x0040, 0x0040, 0x0040, 0x0020, 0x0020, 0x0020, 0x0020, 0x0020, 0x0020, 0x0020, 0x0020, 0x0020, 0x0020, 0x0020, 0x0020, 0x0020, 0x0020, 0x0040, 0x0020, 0x0020, 0x0020, 0x0CA8", "protocol": "RC5", "subdevice": "-1", "deviceName": "Surround Receiver", "device": "16", "key_name": "TUNER A", "company": "Arcam", "code_len": 28, "remoteName": "16_-1", "key_code": "3"},
{"pronto_code": "0x0000, 0x0073, 0x0000, 0x000C, 0x0020, 0x0020, 0x0040, 0x0040, 0x0040, 0x0020, 0x0020, 0x0020, 0x0020, 0x0020, 0x0020, 0x0020, 0x0020, 0x0020, 0x0020, 0x0020, 0x0020, 0x0020, 0x0020, 0x0040, 0x0020, 0x0020, 0x0020, 0x0CA8", "protocol": "RC5", "subdevice": "-1", "deviceName": "Surround Receiver", "device": "16", "key_name": "TUNER B", "company": "Arcam", "code_len": 28, "remoteName": "16_-1", "key_code": "3"},
{"pronto_code": "0x0000, 0x0073, 0x0000, 0x000B, 0x0020, 0x0020, 0x0040, 0x0040, 0x0040, 0x0020, 0x0020, 0x0020, 0x0020, 0x0020, 0x0020, 0x0020, 0x0020, 0x0020, 0x0020, 0x0020, 0x0020, 0x0040, 0x0040, 0x0020, 0x0020, 0x0CC8", "protocol": "RC5", "subdevice": "-1", "deviceName": "Surround Receiver", "device": "16", "key_name": "DVD A", "company": "Arcam", "code_len": 26, "remoteName": "16_-1", "key_code": "4"},
{"pronto_code": "0x0000, 0x0073, 0x0000, 0x000B, 0x0020, 0x0020, 0x0040, 0x0040, 0x0040, 0x0020, 0x0020, 0x0020, 0x0020, 0x0020, 0x0020, 0x0020, 0x0020, 0x0020, 0x0020, 0x0020, 0x0020, 0x0040, 0x0040, 0x0020, 0x0020, 0x0CC8", "protocol": "RC5", "subdevice": "-1", "deviceName": "Surround Receiver", "device": "16", "key_name": "DVD B", "company": "Arcam", "code_len": 26, "remoteName": "16_-1", "key_code": "4"},
{"pronto_code": "0x0000, 0x0073, 0x0000, 0x000B, 0x0020, 0x0020, 0x0040, 0x0040, 0x0040, 0x0020, 0x0020, 0x0020, 0x0020, 0x0020, 0x0020, 0x0020, 0x0020, 0x0020, 0x0020, 0x0020, 0x0020, 0x0040, 0x0040, 0x0040, 0x0020, 0x0CA8", "protocol": "RC5", "subdevice": "-1", "deviceName": "Surround Receiver", "device": "16", "key_name": "TAPE A", "company": "Arcam", "code_len": 26, "remoteName": "16_-1", "key_code": "5"},
{"pronto_code": "0x0000, 0x0073, 0x0000, 0x000B, 0x0020, 0x0020, 0x0040, 0x0040, 0x0040, 0x0020, 0x0020, 0x0020, 0x0020, 0x0020, 0x0020, 0x0020, 0x0020, 0x0020, 0x0020, 0x0020, 0x0020, 0x0040, 0x0040, 0x0040, 0x0020, 0x0CA8", "protocol": "RC5", "subdevice": "-1", "deviceName": "Surround Receiver", "device": "16", "key_name": "TAPE B", "company": "Arcam", "code_len": 26, "remoteName": "16_-1", "key_code": "5"},
{"pronto_code": "0x0000, 0x0073, 0x0000, 0x000B, 0x0020, 0x0020, 0x0040, 0x0040, 0x0040, 0x0020, 0x0020, 0x0020, 0x0020, 0x0020, 0x0020, 0x0020, 0x0020, 0x0020, 0x0020, 0x0020, 0x0020, 0x0040, 0x0020, 0x0020, 0x0040, 0x0CC8", "protocol": "RC5", "subdevice": "-1", "deviceName": "Surround Receiver", "device": "16", "key_name": "VCR A", "company": "Arcam", "code_len": 26, "remoteName": "16_-1", "key_code": "6"},
{"pronto_code": "0x0000, 0x0073, 0x0000, 0x000B, 0x0020, 0x0020, 0x0040, 0x0040, 0x0040, 0x0020, 0x0020, 0x0020, 0x0020, 0x0020, 0x0020, 0x0020, 0x0020, 0x0020, 0x0020, 0x0020, 0x0020, 0x0040, 0x0020, 0x0020, 0x0040, 0x0CC8", "protocol": "RC5", "subdevice": "-1", "deviceName": "Surround Receiver", "device": "16", "key_name": "VCR B", "company": "Arcam", "code_len": 26, "remoteName": "16_-1", "key_code": "6"},
{"pronto_code": "0x0000, 0x0073, 0x0000, 0x000C, 0x0020, 0x0020, 0x0040, 0x0040, 0x0040, 0x0020, 0x0020, 0x0020, 0x0020, 0x0020, 0x0020, 0x0020, 0x0020, 0x0020, 0x0020, 0x0020, 0x0020, 0x0040, 0x0020, 0x0020, 0x0020, 0x0020, 0x0020, 0x0CA8", "protocol": "RC5", "subdevice": "-1", "deviceName": "Surround Receiver", "device": "16", "key_name": "CD A", "company": "Arcam", "code_len": 28, "remoteName": "16_-1", "key_code": "7"},
{"pronto_code": "0x0000, 0x0073, 0x0000, 0x000C, 0x0020, 0x0020, 0x0040, 0x0040, 0x0040, 0x0020, 0x0020, 0x0020, 0x0020, 0x0020, 0x0020, 0x0020, 0x0020, 0x0020, 0x0020, 0x0020, 0x0020, 0x0040, 0x0020, 0x0020, 0x0020, 0x0020, 0x0020, 0x0CA8", "protocol": "RC5", "subdevice": "-1", "deviceName": "Surround Receiver", "device": "16", "key_name": "CD B", "company": "Arcam", "code_len": 28, "remoteName": "16_-1", "key_code": "7"},
{"pronto_code": "0x0000, 0x0073, 0x0000, 0x000B, 0x0020, 0x0020, 0x0040, 0x0040, 0x0040, 0x0020, 0x0020, 0x0020, 0x0020, 0x0020, 0x0020, 0x0020, 0x0020, 0x0020, 0x0020, 0x0040, 0x0040, 0x0020, 0x0020, 0x0020, 0x0020, 0x0CC8", "protocol": "RC5", "subdevice": "-1", "deviceName": "Surround Receiver", "device": "16", "key_name": "AUX A", "company": "Arcam", "code_len": 26, "remoteName": "16_-1", "key_code": "8"},
{"pronto_code": "0x0000, 0x0073, 0x0000, 0x000B, 0x0020, 0x0020, 0x0040, 0x0040, 0x0040, 0x0020, 0x0020, 0x0020, 0x0020, 0x0020, 0x0020, 0x0020, 0x0020, 0x0020, 0x0020, 0x0040, 0x0040, 0x0020, 0x0020, 0x0020, 0x0020, 0x0CC8", "protocol": "RC5", "subdevice": "-1", "deviceName": "Surround Receiver", "device": "16", "key_name": "AUX B", "company": "Arcam", "code_len": 26, "remoteName": "16_-1", "key_code": "8"},
{"pronto_code": "0x0000, 0x0073, 0x0000, 0x000B, 0x0020, 0x0020, 0x0040, 0x0040, 0x0040, 0x0020, 0x0020, 0x0020, 0x0020, 0x0020, 0x0020, 0x0020, 0x0020, 0x0020, 0x0020, 0x0040, 0x0020, 0x0020, 0x0040, 0x0020, 0x0020, 0x0CC8", "protocol": "RC5", "subdevice": "-1", "deviceName": "Surround Receiver", "device": "16", "key_name": "POWER A", "company": "Arcam", "code_len": 26, "remoteName": "16_-1", "key_code": "12"},
{"pronto_code": "0x0000, 0x0073, 0x0000, 0x000B, 0x0020, 0x0020, 0x0040, 0x0040, 0x0040, 0x0020, 0x0020, 0x0020, 0x0020, 0x0020, 0x0020, 0x0020, 0x0020, 0x0020, 0x0020, 0x0040, 0x0020, 0x0020, 0x0040, 0x0020, 0x0020, 0x0CC8", "protocol": "RC5", "subdevice": "-1", "deviceName": "Surround Receiver", "device": "16", "key_name": "POWER B", "company": "Arcam", "code_len": 26, "remoteName": "16_-1", "key_code": "12"},
{"pronto_code": "0x0000, 0x0073, 0x0000, 0x000B, 0x0020, 0x0020, 0x0040, 0x0040, 0x0040, 0x0020, 0x0020, 0x0020, 0x0020, 0x0020, 0x0020, 0x0020, 0x0020, 0x0020, 0x0020, 0x0040, 0x0020, 0x0020, 0x0040, 0x0040, 0x0020, 0x0CA8", "protocol": "RC5", "subdevice": "-1", "deviceName": "Surround Receiver", "device": "16", "key_name": "MUTE A", "company": "Arcam", "code_len": 26, "remoteName": "16_-1", "key_code": "13"},
{"pronto_code": "0x0000, 0x0073, 0x0000, 0x000B, 0x0020, 0x0020, 0x0040, 0x0040, 0x0040, 0x0020, 0x0020, 0x0020, 0x0020, 0x0020, 0x0020, 0x0020, 0x0020, 0x0020, 0x0020, 0x0040, 0x0020, 0x0020, 0x0040, 0x0040, 0x0020, 0x0CA8", "protocol": "RC5", "subdevice": "-1", "deviceName": "Surround Receiver", "device": "16", "key_name": "MUTE B", "company": "Arcam", "code_len": 26, "remoteName": "16_-1", "key_code": "13"},
{"pronto_code": "0x0000, 0x0073, 0x0000, 0x000B, 0x0020, 0x0020, 0x0040, 0x0040, 0x0040, 0x0020, 0x0020, 0x0020, 0x0020, 0x0020, 0x0020, 0x0020, 0x0020, 0x0040, 0x0040, 0x0020, 0x0020, 0x0020, 0x0020, 0x0020, 0x0020, 0x0CC8", "protocol": "RC5", "subdevice": "-1", "deviceName": "Surround Receiver", "device": "16", "key_name": "VOLUME + A", "company": "Arcam", "code_len": 26, "remoteName": "16_-1", "key_code": "16"},
{"pronto_code": "0x0000, 0x0073, 0x0000, 0x000B, 0x0020, 0x0020, 0x0040, 0x0040, 0x0040, 0x0020, 0x0020, 0x0020, 0x0020, 0x0020, 0x0020, 0x0020, 0x0020, 0x0040, 0x0040, 0x0020, 0x0020, 0x0020, 0x0020, 0x0020, 0x0020, 0x0CC8", "protocol": "RC5", "subdevice": "-1", "deviceName": "Surround Receiver", "device": "16", "key_name": "VOLUME + B", "company": "Arcam", "code_len": 26, "remoteName": "16_-1", "key_code": "16"},
{"pronto_code": "0x0000, 0x0073, 0x0000, 0x000B, 0x0020, 0x0020, 0x0040, 0x0040, 0x0040, 0x0020, 0x0020, 0x0020, 0x0020, 0x0020, 0x0020, 0x0020, 0x0020, 0x0040, 0x0040, 0x0020, 0x0020, 0x0020, 0x0020, 0x0040, 0x0020, 0x0CA8", "protocol": "RC5", "subdevice": "-1", "deviceName": "Surround Receiver", "device": "16", "key_name": "VOLUME - A", "company": "Arcam", "code_len": 26, "remoteName": "16_-1", "key_code": "17"},
{"pronto_code": "0x0000, 0x0073, 0x0000, 0x000B, 0x0020, 0x0020, 0x0040, 0x0040, 0x0040, 0x0020, 0x0020, 0x0020, 0x0020, 0x0020, 0x0020, 0x0020, 0x0020, 0x0040, 0x0040, 0x0020, 0x0020, 0x0020, 0x0020, 0x0040, 0x0020, 0x0CA8", "protocol": "RC5", "subdevice": "-1", "deviceName": "Surround Receiver", "device": "16", "key_name": "VOLUME - B", "company": "Arcam", "code_len": 26, "remoteName": "16_-1", "key_code": "17"}
]